{
  "member_id": "H-0016",
  "handle": "abe_keishi",
  "source": "X",
  "url": "https://x.com/abe_keishi",
  "count": 13,
  "posts": [
    {
      "date": "Oct 28, 2025",
      "text": "📣日本維新の会 党員大募集📣 阿部けいしの活動を応援いただける方を募集しております！ 皆様のご参加が、日本の改革を前に進める力となります✨ 党費: 年額2,000円（入党日～翌年3月末） お申込みは、以下のホームページからお願い致します👍🏻 abekeishi.com/joinus#阿部けいし#日本維新の会",
      "author": "abe_keishi",
      "own": true,
      "url": "https://x.com/abe_keishi/status/1983000222658920468"
    },
    {
      "date": "1h",
      "text": "「核の時代」に直面している現在、日本維新の会は、3正面の核の脅威を現実の問題として真正面から捉え、以下を提言しました。 ❶ 核抑⽌を国家安全保障戦略の中⼼概念として位置付ける(核軍縮と核抑止は二項対立ではない) ❷日米拡大抑止協議の運用深化",
      "author": "abe_keishi",
      "own": true,
      "url": "https://x.com/abe_keishi/status/2073985014472315248"
    },
    {
      "date": "6h",
      "text": "【本日22:00〜 プレミア公開！】 いつも「阿部けいしチャンネル」を応援いただき、本当にありがとうございます！ 先日、私が出演させていただき、大変多くの反響をいただいた大人気政治・経済YouTube番組『ReHacQ（リハック）』。ご覧いただいた皆さま、本当にありがとうございました！",
      "author": "abe_keishi",
      "own": true,
      "url": "https://x.com/abe_keishi/status/2073905485200392280"
    },
    {
      "date": "16h",
      "text": "安倍氏が「高市さん応援してあげて」 木原氏、首相と関係深める発端に…回顧展で振り返る sankei.com/article/202607… 木原氏によると、総裁選まで首相とちゃんと話をしたことがなかったが、安倍氏から電話で「高市さんを応援してあげてよ」と依頼され、陣営の選対事務局長に就任した。 安倍氏が「高市さん応援してあげて」 木原氏、首相と関係深める発端に…回顧展で振り返るFrom sankei.com 67 303 1.9K",
      "author": "Sankei_news",
      "own": false,
      "url": "https://x.com/Sankei_news/status/2073750029937131676"
    },
    {
      "date": "18h",
      "text": "【山口太鼓の会の練習に参加‼️🥁】 本日は、西宮市山口町の山口太鼓の会の練習会に参加させていただきました。 10歳から70代まで幅広い世代の皆様が一つになって太鼓に取り組まれる姿が、とても印象的でした。世代を超えて地域の伝統文化が受け継がれていることを心強く感じました。",
      "author": "abe_keishi",
      "own": true,
      "url": "https://x.com/abe_keishi/status/2073723678253309977"
    },
    {
      "date": "19h",
      "text": "兵庫県隊友会総会に出席し、ご挨拶いたしました。12月の政府の戦略３文書改定に向け、国防力を強化することをお誓いしました。 #阿部けいし#日本維新の会#兵庫２区#神戸#西宮",
      "author": "abe_keishi",
      "own": true,
      "url": "https://x.com/abe_keishi/status/2073705884648399146"
    },
    {
      "date": "Jul 3",
      "text": "今夜22時プレミア公開です。 ↓ 【緊急配信】野党の審議拒否に物申す。 youtu.be/tGGNp-00aII?si…@YouTubeより youtube.com 【緊急配信】野党の審議拒否に物申す。国民は年中働いているのに、なぜ国会議員はサボっていいのか？【藤田文武】 いつも藤田文武チャンネルをご視聴いただき、ありがとうございます。「国民は毎日必死に働いているのに、なぜ国会議員は職場（国会）を放... 256 338 1.6K",
      "author": "fumi_fuji",
      "own": false,
      "url": "https://x.com/fumi_fuji/status/2072973806965231826"
    },
    {
      "date": "Jul 5",
      "text": "憲法9条改正について、「自衛隊明記案」と「憲法９条２項削除と国防軍創設案」の違いについて解説しました。「自衛隊明記案」では不十分であり、「憲法９条２項削除と国防軍創設案」が必要となった理由は、「脅威認識が高まったから」というシンプルな理由です。",
      "author": "abe_keishi",
      "own": true,
      "url": "https://x.com/abe_keishi/status/2073571602378481948"
    },
    {
      "date": "Jul 4",
      "text": "米国建国250周年の独立記念日に際し、@realDonaldTrump大統領と米国民の皆様に心からお祝いを申し上げます。 この記念すべき年を祝うべく、日本からは250本の桜が贈られました。 また、米国各地の独立記念日行事で日本の花火が打ち上げられ、お祝いに花を添える予定です。",
      "author": "takaichi_sanae",
      "own": false,
      "url": "https://x.com/takaichi_sanae/status/2073263515952201827"
    },
    {
      "date": "Jul 4",
      "text": "久々のWHO事務局長選挙。来年5月の投票日まで、世界中を舞台に選挙戦が繰り広げられます。我が国の投票先はまだ決まっておりませんが、候補者であるインドネシアのブディ保健大臣から、情熱・意欲溢れるお話を伺いました。",
      "author": "abe_keishi",
      "own": true,
      "url": "https://x.com/abe_keishi/status/2073311257344791023"
    },
    {
      "date": "Jul 3",
      "text": "昨日、「骨太の方針原案2026」の1ページ目を見てびっくりしました。曰く ・我が国の潜在成長率は、長年にわたる「未来への投資不足」により ・官民が連携して大規模かつ長期的な財政支出を伴う産業政策 ・経済財政運営の在り方そのものに関するコペルニクス的転回であり",
      "author": "YOKOTA_Ishin",
      "own": false,
      "url": "https://x.com/YOKOTA_Ishin/status/2073048445791907894"
    },
    {
      "date": "Jul 3",
      "text": "【日本発の次世代エネルギーを世界へ】 昨日、次世代太陽電池として期待される「ペロブスカイト太陽電池」の実用化に向けた提言を木原官房長官に提出しました。",
      "author": "baba_ishin",
      "own": false,
      "url": "https://x.com/baba_ishin/status/2073013671979298882"
    },
    {
      "date": "Jul 3",
      "text": "赤澤大臣、エネルギー安全保障に関する提言をお受け取り頂き、ありがとうございました。我が国のエネルギー安保の向上に向けた平素よりのご尽力に、心より感謝申し上げます‼️ 赤沢りょうせい @ryosei_akazawa [Jul 3](https://x.com/ryosei_akazawa",
      "author": "abe_keishi",
      "own": true,
      "url": "https://x.com/abe_keishi/status/2073014889866748340"
    }
  ]
}