{
  "speaker": "熊谷 裕人",
  "url": "https://kokkai.ndl.go.jp/api/speech?speaker=%E7%86%8A%E8%B0%B7+%E8%A3%95%E4%BA%BA&recordPacking=json&maximumRecords=30&startRecord=271&from=2022-01-01",
  "count": 205,
  "dropped_other_speaker": 95,
  "speeches": [
    {
      "date": "2026-06-16",
      "meeting": "文教科学委員会",
      "house": "参議院",
      "speaker": "熊谷裕人",
      "speech": "○委員長（熊谷裕人君）　ただいまから文教科学委員会を開会いたします。\r\n　政府参考人の出席要求に関する件についてお諮りいたします。\r\n　著作権法の一部を改正する法律案の審査のため、本日の委員会に、理事会協議のとおり、文部科学省初等中等教育局長望月禎さん外二名を政府参考人として出席を求め、その説明を聴取することに御異議ございませんか。\r\n　　　〔「異議なし」と呼ぶ者あり〕",
      "url": "https://kokkai.ndl.go.jp/txt/122115104X01120260616/1"
    },
    {
      "date": "2026-06-16",
      "meeting": "文教科学委員会",
      "house": "参議院",
      "speaker": "熊谷裕人",
      "speech": "○委員長（熊谷裕人君）　御異議ないと認め、さよう決定いたします。\r\n　　　　─────────────",
      "url": "https://kokkai.ndl.go.jp/txt/122115104X01120260616/2"
    },
    {
      "date": "2026-06-16",
      "meeting": "文教科学委員会",
      "house": "参議院",
      "speaker": "熊谷裕人",
      "speech": "○委員長（熊谷裕人君）　著作権法の一部を改正する法律案を議題といたします。\r\n　本案の趣旨説明は既に聴取しておりますので、これより質疑に入ります。\r\n　質疑のある方は順次御発言願います。",
      "url": "https://kokkai.ndl.go.jp/txt/122115104X01120260616/3"
    },
    {
      "date": "2026-06-16",
      "meeting": "文教科学委員会",
      "house": "参議院",
      "speaker": "熊谷裕人",
      "speech": "○委員長（熊谷裕人君）　この際、委員の異動について御報告いたします。\r\n　本日、片山さつきさんが委員を辞任され、その補欠として滝波宏文さんが選任されました。\r\n　　　　─────────────",
      "url": "https://kokkai.ndl.go.jp/txt/122115104X01120260616/100"
    },
    {
      "date": "2026-06-16",
      "meeting": "文教科学委員会",
      "house": "参議院",
      "speaker": "熊谷裕人",
      "speech": "○委員長（熊谷裕人君）　他に御発言もないようですから、質疑は終局したものと認めます。\r\n　これより討論に入ります。──別に御意見もないようですから、これより直ちに採決に入ります。\r\n　著作権法の一部を改正する法律案に賛成の方の挙手を願います。\r\n　　　〔賛成者挙手〕",
      "url": "https://kokkai.ndl.go.jp/txt/122115104X01120260616/116"
    },
    {
      "date": "2026-06-16",
      "meeting": "文教科学委員会",
      "house": "参議院",
      "speaker": "熊谷裕人",
      "speech": "○委員長（熊谷裕人君）　全会一致と認めます。よって、本案は全会一致をもって原案どおり可決すべきものと決定いたしました。\r\n　この際、古賀さんから発言を求められておりますので、これを許します。古賀千景さん。",
      "url": "https://kokkai.ndl.go.jp/txt/122115104X01120260616/117"
    },
    {
      "date": "2026-06-16",
      "meeting": "文教科学委員会",
      "house": "参議院",
      "speaker": "熊谷裕人",
      "speech": "○委員長（熊谷裕人君）　ただいま古賀さんから提出されました附帯決議案を議題とし、採決を行います。\r\n　本附帯決議案に賛成の方の挙手を願います。\r\n　　　〔賛成者挙手〕",
      "url": "https://kokkai.ndl.go.jp/txt/122115104X01120260616/119"
    },
    {
      "date": "2026-06-16",
      "meeting": "文教科学委員会",
      "house": "参議院",
      "speaker": "熊谷裕人",
      "speech": "○委員長（熊谷裕人君）　全会一致と認めます。よって、古賀さん提出の附帯決議案は全会一致をもって本委員会の決議とすることに決定いたしました。\r\n　ただいまの決議に対し、松本文部科学大臣から発言を求められておりますので、この際、これを許します。松本文部科学大臣。",
      "url": "https://kokkai.ndl.go.jp/txt/122115104X01120260616/120"
    },
    {
      "date": "2026-06-16",
      "meeting": "文教科学委員会",
      "house": "参議院",
      "speaker": "熊谷裕人",
      "speech": "○委員長（熊谷裕人君）　なお、審査報告書の作成につきましては、これを委員長に御一任願いたいと存じますが、御異議ございませんか。\r\n　　　〔「異議なし」と呼ぶ者あり〕",
      "url": "https://kokkai.ndl.go.jp/txt/122115104X01120260616/122"
    },
    {
      "date": "2026-06-16",
      "meeting": "文教科学委員会",
      "house": "参議院",
      "speaker": "熊谷裕人",
      "speech": "○委員長（熊谷裕人君）　御異議ないと認め、さよう決定いたします。\r\n　本日はこれにて散会いたします。\r\n　　　午後零時四十四分散会",
      "url": "https://kokkai.ndl.go.jp/txt/122115104X01120260616/123"
    },
    {
      "date": "2026-06-11",
      "meeting": "文教科学委員会",
      "house": "参議院",
      "speaker": "熊谷裕人",
      "speech": "○委員長（熊谷裕人君）　ただいまから文教科学委員会を開会いたします。\r\n　委員の異動について御報告いたします。\r\n　昨日、滝波宏文さんが委員を辞任され、その補欠として片山さつきさんが選任されました。\r\n　　　　─────────────",
      "url": "https://kokkai.ndl.go.jp/txt/122115104X01020260611/1"
    },
    {
      "date": "2026-06-11",
      "meeting": "文教科学委員会",
      "house": "参議院",
      "speaker": "熊谷裕人",
      "speech": "○委員長（熊谷裕人君）　政府参考人の出席要求に関する件についてお諮りいたします。\r\n　教育、文化、スポーツ、学術及び科学技術に関する調査のため、本日の委員会に、理事会協議のとおり、内閣府大臣官房審議官由布和嘉子さん外六名を政府参考人として出席を求め、その説明を聴取することに御異議ございませんか。\r\n　　　〔「異議なし」と呼ぶ者あり〕",
      "url": "https://kokkai.ndl.go.jp/txt/122115104X01020260611/2"
    },
    {
      "date": "2026-06-11",
      "meeting": "文教科学委員会",
      "house": "参議院",
      "speaker": "熊谷裕人",
      "speech": "○委員長（熊谷裕人君）　御異議なしと認め、さよう決定いたします。\r\n　　　　─────────────",
      "url": "https://kokkai.ndl.go.jp/txt/122115104X01020260611/3"
    },
    {
      "date": "2026-06-11",
      "meeting": "文教科学委員会",
      "house": "参議院",
      "speaker": "熊谷裕人",
      "speech": "○委員長（熊谷裕人君）　教育、文化、スポーツ、学術及び科学技術に関する調査を議題とし、質疑を行います。\r\n　質疑のある方は順次御発言願います。",
      "url": "https://kokkai.ndl.go.jp/txt/122115104X01020260611/4"
    },
    {
      "date": "2026-06-11",
      "meeting": "文教科学委員会",
      "house": "参議院",
      "speaker": "熊谷裕人",
      "speech": "○委員長（熊谷裕人君）　速記をちょっと止めて。\r\n　　　〔速記中止〕",
      "url": "https://kokkai.ndl.go.jp/txt/122115104X01020260611/38"
    },
    {
      "date": "2026-06-11",
      "meeting": "文教科学委員会",
      "house": "参議院",
      "speaker": "熊谷裕人",
      "speech": "○委員長（熊谷裕人君）　速記を起こしてください。\r\n　それでは、松本大臣、お願いします。",
      "url": "https://kokkai.ndl.go.jp/txt/122115104X01020260611/39"
    },
    {
      "date": "2026-06-11",
      "meeting": "文教科学委員会",
      "house": "参議院",
      "speaker": "熊谷裕人",
      "speech": "○委員長（熊谷裕人君）　ただいまの件につきましては、後刻理事会において協議いたします。",
      "url": "https://kokkai.ndl.go.jp/txt/122115104X01020260611/109"
    },
    {
      "date": "2026-06-11",
      "meeting": "文教科学委員会",
      "house": "参議院",
      "speaker": "熊谷裕人",
      "speech": "○委員長（熊谷裕人君）　本日の調査はこの程度にとどめます。\r\n　　　　─────────────",
      "url": "https://kokkai.ndl.go.jp/txt/122115104X01020260611/115"
    },
    {
      "date": "2026-06-11",
      "meeting": "文教科学委員会",
      "house": "参議院",
      "speaker": "熊谷裕人",
      "speech": "○委員長（熊谷裕人君）　次に、著作権法の一部を改正する法律案を議題といたします。\r\n　政府から趣旨説明を聴取いたします。松本文部科学大臣。",
      "url": "https://kokkai.ndl.go.jp/txt/122115104X01020260611/116"
    },
    {
      "date": "2026-06-11",
      "meeting": "文教科学委員会",
      "house": "参議院",
      "speaker": "熊谷裕人",
      "speech": "○委員長（熊谷裕人君）　以上で趣旨説明の聴取は終わりました。\r\n　本案に対する質疑は後日に譲ることとし、本日はこれにて散会いたします。\r\n　　　午後零時六分散会",
      "url": "https://kokkai.ndl.go.jp/txt/122115104X01020260611/118"
    },
    {
      "date": "2026-06-09",
      "meeting": "文教科学委員会",
      "house": "参議院",
      "speaker": "熊谷裕人",
      "speech": "○委員長（熊谷裕人君）　ただいまから文教科学委員会を開会いたします。\r\n　委員の異動について御報告いたします。\r\n　昨日までに、石橋通宏さんが委員を辞任され、その補欠として勝部賢志さんが選任されました。\r\n　　　　─────────────",
      "url": "https://kokkai.ndl.go.jp/txt/122115104X00920260609/1"
    },
    {
      "date": "2026-06-09",
      "meeting": "文教科学委員会",
      "house": "参議院",
      "speaker": "熊谷裕人",
      "speech": "○委員長（熊谷裕人君）　政府参考人の出席要求に関する件についてお諮りいたします。\r\n　学校教育法等の一部を改正する法律案の審査のため、本日の委員会に、理事会協議のとおり、こども家庭庁長官官房審議官竹林悟史さん外四名を政府参考人として出席を求め、その説明を聴取することに御異議ございませんか。\r\n　　　〔「異議なし」と呼ぶ者あり〕",
      "url": "https://kokkai.ndl.go.jp/txt/122115104X00920260609/2"
    },
    {
      "date": "2026-06-09",
      "meeting": "文教科学委員会",
      "house": "参議院",
      "speaker": "熊谷裕人",
      "speech": "○委員長（熊谷裕人君）　御異議ないと認め、さよう決定いたします。\r\n　　　　─────────────",
      "url": "https://kokkai.ndl.go.jp/txt/122115104X00920260609/3"
    },
    {
      "date": "2026-06-09",
      "meeting": "文教科学委員会",
      "house": "参議院",
      "speaker": "熊谷裕人",
      "speech": "○委員長（熊谷裕人君）　学校教育法等の一部を改正する法律案を議題とし、質疑を行います。\r\n　質疑のある方は順次御発言願います。",
      "url": "https://kokkai.ndl.go.jp/txt/122115104X00920260609/4"
    },
    {
      "date": "2026-06-09",
      "meeting": "文教科学委員会",
      "house": "参議院",
      "speaker": "熊谷裕人",
      "speech": "○委員長（熊谷裕人君）　この際、委員の異動について御報告いたします。\r\n　本日、片山さつきさんが委員を辞任され、その補欠として滝波宏文さんが選任されました。\r\n　　　　─────────────",
      "url": "https://kokkai.ndl.go.jp/txt/122115104X00920260609/50"
    },
    {
      "date": "2026-06-09",
      "meeting": "文教科学委員会",
      "house": "参議院",
      "speaker": "熊谷裕人",
      "speech": "○委員長（熊谷裕人君）　他に御発言もないようですから、質疑は終局したものと認めます。\r\n　これより討論に入ります。\r\n　御意見のある方は賛否を明らかにしてお述べ願います。",
      "url": "https://kokkai.ndl.go.jp/txt/122115104X00920260609/68"
    },
    {
      "date": "2026-06-09",
      "meeting": "文教科学委員会",
      "house": "参議院",
      "speaker": "熊谷裕人",
      "speech": "○委員長（熊谷裕人君）　他に御意見もないようですから、討論は終局したものと認めます。\r\n　これより採決に入ります。\r\n　学校教育法等の一部を改正する法律案に賛成の方の挙手を願います。\r\n　　　〔賛成者挙手〕",
      "url": "https://kokkai.ndl.go.jp/txt/122115104X00920260609/71"
    },
    {
      "date": "2026-06-09",
      "meeting": "文教科学委員会",
      "house": "参議院",
      "speaker": "熊谷裕人",
      "speech": "○委員長（熊谷裕人君）　多数と認めます。よって、本案は多数をもって原案どおり可決すべきものと決定いたしました。\r\n　この際、古賀さんから発言を求められておりますので、これを許します。古賀千景さん。",
      "url": "https://kokkai.ndl.go.jp/txt/122115104X00920260609/72"
    },
    {
      "date": "2026-06-09",
      "meeting": "文教科学委員会",
      "house": "参議院",
      "speaker": "熊谷裕人",
      "speech": "○委員長（熊谷裕人君）　ただいま古賀さんから提出されました附帯決議案を議題とし、採決を行います。\r\n　本附帯決議案に賛成の方の挙手を願います。\r\n　　　〔賛成者挙手〕",
      "url": "https://kokkai.ndl.go.jp/txt/122115104X00920260609/74"
    },
    {
      "date": "2026-06-09",
      "meeting": "文教科学委員会",
      "house": "参議院",
      "speaker": "熊谷裕人",
      "speech": "○委員長（熊谷裕人君）　多数と認めます。よって、古賀さん提出の附帯決議案は多数をもって本委員会の決議とすることに決定いたしました。\r\n　ただいまの決議に対し、松本文部科学大臣から発言を求められておりますので、この際、これを許します。松本文部科学大臣。",
      "url": "https://kokkai.ndl.go.jp/txt/122115104X00920260609/75"
    },
    {
      "date": "2026-06-09",
      "meeting": "文教科学委員会",
      "house": "参議院",
      "speaker": "熊谷裕人",
      "speech": "○委員長（熊谷裕人君）　なお、審査報告書の作成につきましては、これを委員長に御一任願いたいと存じますが、御異議ございませんか。\r\n　　　〔「異議なし」と呼ぶ者あり〕",
      "url": "https://kokkai.ndl.go.jp/txt/122115104X00920260609/77"
    },
    {
      "date": "2026-06-09",
      "meeting": "文教科学委員会",
      "house": "参議院",
      "speaker": "熊谷裕人",
      "speech": "○委員長（熊谷裕人君）　御異議ないと認め、さよう決定いたします。\r\n　本日はこれにて散会いたします。\r\n　　　午前十一時四十五分散会",
      "url": "https://kokkai.ndl.go.jp/txt/122115104X00920260609/78"
    },
    {
      "date": "2026-06-02",
      "meeting": "文教科学委員会",
      "house": "参議院",
      "speaker": "熊谷裕人",
      "speech": "○委員長（熊谷裕人君）　ただいまから文教科学委員会を開会いたします。\r\n　委員の異動について御報告いたします。\r\n　昨日までに、朝日健太郎さん及び勝部賢志さんが委員を辞任され、その補欠として上野通子さん及び石橋通宏さんが選任されました。\r\n　　　　─────────────",
      "url": "https://kokkai.ndl.go.jp/txt/122115104X00820260602/1"
    },
    {
      "date": "2026-06-02",
      "meeting": "文教科学委員会",
      "house": "参議院",
      "speaker": "熊谷裕人",
      "speech": "○委員長（熊谷裕人君）　政府参考人の出席要求に関する件についてお諮りいたします。\r\n　学校教育法等の一部を改正する法律案の審査のため、本日の委員会に、理事会協議のとおり、文部科学省大臣官房学習基盤審議官堀野晶三さん外一名を政府参考人として出席を求め、その説明を聴取することに御異議ございませんか。\r\n　　　〔「異議なし」と呼ぶ者あり〕",
      "url": "https://kokkai.ndl.go.jp/txt/122115104X00820260602/2"
    },
    {
      "date": "2026-06-02",
      "meeting": "文教科学委員会",
      "house": "参議院",
      "speaker": "熊谷裕人",
      "speech": "○委員長（熊谷裕人君）　御異議なしと認め、さよう決定いたします。\r\n　　　　─────────────",
      "url": "https://kokkai.ndl.go.jp/txt/122115104X00820260602/3"
    },
    {
      "date": "2026-06-02",
      "meeting": "文教科学委員会",
      "house": "参議院",
      "speaker": "熊谷裕人",
      "speech": "○委員長（熊谷裕人君）　学校教育法等の一部を改正する法律案を議題といたします。\r\n　政府から趣旨説明を聴取いたします。松本文部科学大臣。",
      "url": "https://kokkai.ndl.go.jp/txt/122115104X00820260602/4"
    },
    {
      "date": "2026-06-02",
      "meeting": "文教科学委員会",
      "house": "参議院",
      "speaker": "熊谷裕人",
      "speech": "○委員長（熊谷裕人君）　以上で趣旨説明の聴取は終わりました。\r\n　これより質疑に入ります。\r\n　質疑のある方は順次御発言願います。",
      "url": "https://kokkai.ndl.go.jp/txt/122115104X00820260602/6"
    },
    {
      "date": "2026-06-02",
      "meeting": "文教科学委員会",
      "house": "参議院",
      "speaker": "熊谷裕人",
      "speech": "○委員長（熊谷裕人君）　本日の質疑はこの程度にとどめ、これにて散会いたします。\r\n　　　午前十一時四十九分散会",
      "url": "https://kokkai.ndl.go.jp/txt/122115104X00820260602/82"
    },
    {
      "date": "2026-05-21",
      "meeting": "文教科学委員会",
      "house": "参議院",
      "speaker": "熊谷裕人",
      "speech": "○委員長（熊谷裕人君）　ただいまから文教科学委員会を開会いたします。\r\n　委員の異動について御報告いたします。\r\n　昨日、上野通子さんが委員を辞任され、その補欠として朝日健太郎さんが選任されました。\r\n　　　　─────────────",
      "url": "https://kokkai.ndl.go.jp/txt/122115104X00720260521/1"
    },
    {
      "date": "2026-05-21",
      "meeting": "文教科学委員会",
      "house": "参議院",
      "speaker": "熊谷裕人",
      "speech": "○委員長（熊谷裕人君）　政府参考人の出席要求に関する件についてお諮りいたします。\r\n　教育、文化、スポーツ、学術及び科学技術に関する調査のため、本日の委員会に、理事会協議のとおり、文部科学省総合教育政策局長塩見みづ枝さん外三名を政府参考人として出席を求め、その説明を聴取することに御異議ございませんか。\r\n　　　〔「異議なし」と呼ぶ者あり〕",
      "url": "https://kokkai.ndl.go.jp/txt/122115104X00720260521/2"
    },
    {
      "date": "2026-05-21",
      "meeting": "文教科学委員会",
      "house": "参議院",
      "speaker": "熊谷裕人",
      "speech": "○委員長（熊谷裕人君）　御異議なしと認め、さよう決定いたします。\r\n　　　　─────────────",
      "url": "https://kokkai.ndl.go.jp/txt/122115104X00720260521/3"
    },
    {
      "date": "2026-05-21",
      "meeting": "文教科学委員会",
      "house": "参議院",
      "speaker": "熊谷裕人",
      "speech": "○委員長（熊谷裕人君）　教育、文化、スポーツ、学術及び科学技術に関する調査を議題とし、質疑を行います。\r\n　質疑のある方は順次御発言願います。",
      "url": "https://kokkai.ndl.go.jp/txt/122115104X00720260521/4"
    },
    {
      "date": "2026-05-21",
      "meeting": "文教科学委員会",
      "house": "参議院",
      "speaker": "熊谷裕人",
      "speech": "○委員長（熊谷裕人君）　大丈夫ですか。\r\n　速記を止めてください。\r\n　　　〔速記中止〕",
      "url": "https://kokkai.ndl.go.jp/txt/122115104X00720260521/45"
    },
    {
      "date": "2026-05-21",
      "meeting": "文教科学委員会",
      "house": "参議院",
      "speaker": "熊谷裕人",
      "speech": "○委員長（熊谷裕人君）　速記を起こしてください。",
      "url": "https://kokkai.ndl.go.jp/txt/122115104X00720260521/46"
    },
    {
      "date": "2026-05-21",
      "meeting": "文教科学委員会",
      "house": "参議院",
      "speaker": "熊谷裕人",
      "speech": "○委員長（熊谷裕人君）　ただいまの件につきましては、理事会で協議をさせていただきます。",
      "url": "https://kokkai.ndl.go.jp/txt/122115104X00720260521/51"
    },
    {
      "date": "2026-05-21",
      "meeting": "文教科学委員会",
      "house": "参議院",
      "speaker": "熊谷裕人",
      "speech": "○委員長（熊谷裕人君）　本日の調査はこの程度にとどめ、これにて散会いたします。\r\n　　　午後零時六分散会",
      "url": "https://kokkai.ndl.go.jp/txt/122115104X00720260521/106"
    },
    {
      "date": "2026-04-21",
      "meeting": "文教科学委員会",
      "house": "参議院",
      "speaker": "熊谷裕人",
      "speech": "○委員長（熊谷裕人君）　ただいまから文教科学委員会を開会いたします。\r\n　政府参考人の出席要求に関する件についてお諮りいたします。\r\n　教育、文化、スポーツ、学術及び科学技術に関する調査のため、本日の委員会に、理事会協議のとおり、警察庁長官官房審議官阿部竜矢さん外十一名を政府参考人として出席を求め、その説明を聴取することに御異議ございませんか。\r\n　　　〔「異議なし」と呼ぶ者あり〕",
      "url": "https://kokkai.ndl.go.jp/txt/122115104X00620260421/1"
    },
    {
      "date": "2026-04-21",
      "meeting": "文教科学委員会",
      "house": "参議院",
      "speaker": "熊谷裕人",
      "speech": "○委員長（熊谷裕人君）　御異議ないと認め、さよう決定いたします。\r\n　　　　─────────────",
      "url": "https://kokkai.ndl.go.jp/txt/122115104X00620260421/2"
    },
    {
      "date": "2026-04-21",
      "meeting": "文教科学委員会",
      "house": "参議院",
      "speaker": "熊谷裕人",
      "speech": "○委員長（熊谷裕人君）　教育、文化、スポーツ、学術及び科学技術に関する調査を議題とし、質疑を行います。\r\n　質疑のある方は順次御発言願います。",
      "url": "https://kokkai.ndl.go.jp/txt/122115104X00620260421/3"
    },
    {
      "date": "2026-04-21",
      "meeting": "文教科学委員会",
      "house": "参議院",
      "speaker": "熊谷裕人",
      "speech": "○委員長（熊谷裕人君）　時間が来ておりますので、おまとめください。",
      "url": "https://kokkai.ndl.go.jp/txt/122115104X00620260421/61"
    },
    {
      "date": "2026-04-21",
      "meeting": "文教科学委員会",
      "house": "参議院",
      "speaker": "熊谷裕人",
      "speech": "○委員長（熊谷裕人君）　本日の調査はこの程度にとどめ、これにて散会いたします。\r\n　　　午後零時十二分散会",
      "url": "https://kokkai.ndl.go.jp/txt/122115104X00620260421/100"
    },
    {
      "date": "2026-04-16",
      "meeting": "文教科学委員会",
      "house": "参議院",
      "speaker": "熊谷裕人",
      "speech": "○委員長（熊谷裕人君）　ただいまから文教科学委員会を開会いたします。\r\n　政府参考人の出席要求に関する件についてお諮りいたします。\r\n　教育、文化、スポーツ、学術及び科学技術に関する調査のため、本日の委員会に、理事会協議のとおり、内閣官房内閣審議官成松英範さん外八名を政府参考人として出席を求め、その説明を聴取することに御異議ございませんか。\r\n　　　〔「異議なし」と呼ぶ者あり〕",
      "url": "https://kokkai.ndl.go.jp/txt/122115104X00520260416/1"
    },
    {
      "date": "2026-04-16",
      "meeting": "文教科学委員会",
      "house": "参議院",
      "speaker": "熊谷裕人",
      "speech": "○委員長（熊谷裕人君）　御異議ないと認め、さよう決定いたします。\r\n　　　　─────────────",
      "url": "https://kokkai.ndl.go.jp/txt/122115104X00520260416/2"
    },
    {
      "date": "2026-04-16",
      "meeting": "文教科学委員会",
      "house": "参議院",
      "speaker": "熊谷裕人",
      "speech": "○委員長（熊谷裕人君）　教育、文化、スポーツ、学術及び科学技術に関する調査のうち、文教科学行政の基本施策に関する件を議題とし、質疑を行います。\r\n　質疑のある方は順次御発言願います。",
      "url": "https://kokkai.ndl.go.jp/txt/122115104X00520260416/3"
    },
    {
      "date": "2026-04-16",
      "meeting": "文教科学委員会",
      "house": "参議院",
      "speaker": "熊谷裕人",
      "speech": "○委員長（熊谷裕人君）　午後一時に再開することとし、休憩いたします。\r\n　　　午前十一時五十二分休憩\r\n　　　　　─────・─────\r\n　　　午後一時開会",
      "url": "https://kokkai.ndl.go.jp/txt/122115104X00520260416/99"
    },
    {
      "date": "2026-04-16",
      "meeting": "文教科学委員会",
      "house": "参議院",
      "speaker": "熊谷裕人",
      "speech": "○委員長（熊谷裕人君）　ただいまから文教科学委員会を再開いたします。\r\n　休憩前に引き続き、教育、文化、スポーツ、学術及び科学技術に関する調査のうち、文教科学行政の基本施策に関する件を議題とし、質疑を行います。\r\n　質疑のある方は順次御発言願います。",
      "url": "https://kokkai.ndl.go.jp/txt/122115104X00520260416/100"
    },
    {
      "date": "2026-04-16",
      "meeting": "文教科学委員会",
      "house": "参議院",
      "speaker": "熊谷裕人",
      "speech": "○委員長（熊谷裕人君）　時間が来ておりますので、簡単にお願いします。",
      "url": "https://kokkai.ndl.go.jp/txt/122115104X00520260416/151"
    },
    {
      "date": "2026-04-16",
      "meeting": "文教科学委員会",
      "house": "参議院",
      "speaker": "熊谷裕人",
      "speech": "○委員長（熊谷裕人君）　ただいまの御提案につきましては、後刻理事会にて協議をいたしたいと思います。",
      "url": "https://kokkai.ndl.go.jp/txt/122115104X00520260416/153"
    },
    {
      "date": "2026-04-16",
      "meeting": "文教科学委員会",
      "house": "参議院",
      "speaker": "熊谷裕人",
      "speech": "○委員長（熊谷裕人君）　まず、大臣お願いします。",
      "url": "https://kokkai.ndl.go.jp/txt/122115104X00520260416/163"
    },
    {
      "date": "2026-04-16",
      "meeting": "文教科学委員会",
      "house": "参議院",
      "speaker": "熊谷裕人",
      "speech": "○委員長（熊谷裕人君）　次に、こども家庭庁長官官房竹林審議官。（発言する者あり）\r\n　それでは、よろしいですか。じゃ、下野さん、どうぞ。",
      "url": "https://kokkai.ndl.go.jp/txt/122115104X00520260416/165"
    },
    {
      "date": "2026-04-16",
      "meeting": "文教科学委員会",
      "house": "参議院",
      "speaker": "熊谷裕人",
      "speech": "○委員長（熊谷裕人君）　よろしいですか。\r\n　もう時間が来ておりますので。（発言する者あり）訂正。じゃ、訂正お願いします。",
      "url": "https://kokkai.ndl.go.jp/txt/122115104X00520260416/179"
    },
    {
      "date": "2026-04-16",
      "meeting": "文教科学委員会",
      "house": "参議院",
      "speaker": "熊谷裕人",
      "speech": "○委員長（熊谷裕人君）　本件に対する質疑はこの程度にとどめ、本日はこれにて散会いたします。\r\n　　　午後三時四十五分散会",
      "url": "https://kokkai.ndl.go.jp/txt/122115104X00520260416/243"
    },
    {
      "date": "2026-04-02",
      "meeting": "文教科学委員会",
      "house": "参議院",
      "speaker": "熊谷裕人",
      "speech": "○委員長（熊谷裕人君）　ただいまから文教科学委員会を開会いたします。\r\n　委員の異動について御報告いたします。\r\n　昨日までに、吉井章さんが委員を辞任され、その補欠として片山さつきさんが選任されました。\r\n　　　　─────────────",
      "url": "https://kokkai.ndl.go.jp/txt/122115104X00420260402/1"
    },
    {
      "date": "2026-04-02",
      "meeting": "文教科学委員会",
      "house": "参議院",
      "speaker": "熊谷裕人",
      "speech": "○委員長（熊谷裕人君）　政府参考人の出席要求に関する件についてお諮りいたします。\r\n　委嘱審査のため、本日の委員会に、理事会協議のとおり、文部科学省大臣官房文教施設企画・防災部長蝦名喜之さん外六名を政府参考人として出席を求め、その説明を聴取することに御異議ございませんか。\r\n　　　〔「異議なし」と呼ぶ者あり〕",
      "url": "https://kokkai.ndl.go.jp/txt/122115104X00420260402/2"
    },
    {
      "date": "2026-04-02",
      "meeting": "文教科学委員会",
      "house": "参議院",
      "speaker": "熊谷裕人",
      "speech": "○委員長（熊谷裕人君）　異議なしと認め、さよう決定いたします。\r\n　　　　─────────────",
      "url": "https://kokkai.ndl.go.jp/txt/122115104X00420260402/3"
    },
    {
      "date": "2026-04-02",
      "meeting": "文教科学委員会",
      "house": "参議院",
      "speaker": "熊谷裕人",
      "speech": "○委員長（熊谷裕人君）　去る三月三十日、予算委員会から、四月二日の一日間、令和八年度一般会計予算、同特別会計予算、同政府関係機関予算中、文部科学省所管について審査の委嘱がありました。\r\n　この際、本件を議題といたします。\r\n　予算の説明につきましては既に聴取しておりますので、これより質疑に入ります。\r\n　質疑のある方は順次御発言願います。",
      "url": "https://kokkai.ndl.go.jp/txt/122115104X00420260402/4"
    },
    {
      "date": "2026-04-02",
      "meeting": "文教科学委員会",
      "house": "参議院",
      "speaker": "熊谷裕人",
      "speech": "○委員長（熊谷裕人君）　午後一時に再開することとし、休憩いたします。\r\n　　　午前十一時五十七分休憩\r\n　　　　　─────・─────\r\n　　　午後一時開会",
      "url": "https://kokkai.ndl.go.jp/txt/122115104X00420260402/104"
    },
    {
      "date": "2026-04-02",
      "meeting": "文教科学委員会",
      "house": "参議院",
      "speaker": "熊谷裕人",
      "speech": "○委員長（熊谷裕人君）　ただいまから文教科学委員会を再開いたします。\r\n　休憩前に引き続き、令和八年度総予算の委嘱審査を行います。\r\n　質疑のある方は順次御発言願います。",
      "url": "https://kokkai.ndl.go.jp/txt/122115104X00420260402/105"
    },
    {
      "date": "2026-04-02",
      "meeting": "文教科学委員会",
      "house": "参議院",
      "speaker": "熊谷裕人",
      "speech": "○委員長（熊谷裕人君）　以上をもちまして、令和八年度一般会計予算、同特別会計予算、同政府関係機関予算中、文部科学省所管についての委嘱審査は終了いたしました。\r\n　なお、委嘱審査報告書の作成につきましては、これを委員長に御一任願いたいと存じますが、御異議ございませんか。\r\n　　　〔「異議なし」と呼ぶ者あり〕",
      "url": "https://kokkai.ndl.go.jp/txt/122115104X00420260402/172"
    },
    {
      "date": "2026-04-02",
      "meeting": "文教科学委員会",
      "house": "参議院",
      "speaker": "熊谷裕人",
      "speech": "○委員長（熊谷裕人君）　御異議ないと認め、さよう決定いたします。\r\n　本日はこれにて散会いたします。\r\n　　　午後二時三十四分散会",
      "url": "https://kokkai.ndl.go.jp/txt/122115104X00420260402/173"
    },
    {
      "date": "2026-03-31",
      "meeting": "本会議",
      "house": "参議院",
      "speaker": "熊谷裕人",
      "speech": "○熊谷裕人君　ただいま議題となりました両法律案につきまして、文教科学委員会における審査の経過と結果を御報告申し上げます。\r\n　まず、高等学校等就学支援金の支給に関する法律の一部を改正する法律案は、高等学校等就学支援金の支給について、保護者等の収入の状況を勘案しないこととする等の措置を講じようとするものであります。\r\n　委員会におきましては、法律の目的を改正する理由、支給対象者の見直しの是非、公立高校等への支援の在り方等について質疑が行われましたが、その詳細は会議録によって御承知願いたいと存じます。\r\n　質疑を終局した後、日本共産党の吉良委員より、国籍及び在留資格等に基づく支給対象者の見直しに係る規定を削除すること等を内容とする修正案が提出されました。\r\n　これに伴い、国会法第五十七条の三の規定に基づいて内閣から意見を聴取いたしましたところ、修正案に反対である旨の意見が述べられました。\r\n　次いで、討論に入りましたところ、参政党の後藤委員より原案及び修正案に反対の意見が述べられました。\r\n　討論を終局し、順次採決の結果、修正案は否決され、本法律案は多数をもって原案どおり可決すべきものと決定いたしました。\r\n　なお、本法律案に対して附帯決議が付されております。\r\n　次に、公立義務教育諸学校の学級編制及び教職員定数の標準に関する法律の一部を改正する法律案は、公立の中学校等の学級編制の標準及び公立の義務教育諸学校の教職員定数の標準を改めようとするものであります。\r\n　委員会におきましては、三十五人学級の効果、教員確保のための取組、教職員定数拡充の必要性等について質疑が行われましたが、その詳細は会議録によって御承知願いたいと存じます。\r\n　質疑を終局した後、日本共産党の吉良委員より、事務職員の複数配置に係る算定基準を引き下げること等を内容とする修正案が提出されました。\r\n　次いで、順次採決の結果、修正案は否決され、本法律案は全会一致をもって原案どおり可決すべきものと決定いたしました。\r\n　なお、本法律案に対して附帯決議が付されております。\r\n　以上、御報告申し上げます。（拍手）\r\n　　　　─────────────",
      "url": "https://kokkai.ndl.go.jp/txt/122115254X00720260331/18"
    },
    {
      "date": "2026-03-31",
      "meeting": "文教科学委員会",
      "house": "参議院",
      "speaker": "熊谷裕人",
      "speech": "○委員長（熊谷裕人君）　ただいまから文教科学委員会を開会いたします。\r\n　委員の異動について御報告いたします。\r\n　昨日、かまやち敏さん及び片山さつきさんが委員を辞任され、その補欠として上野通子さん及び吉井章さんが選任されました。\r\n　　　　─────────────",
      "url": "https://kokkai.ndl.go.jp/txt/122115104X00320260331/1"
    },
    {
      "date": "2026-03-31",
      "meeting": "文教科学委員会",
      "house": "参議院",
      "speaker": "熊谷裕人",
      "speech": "○委員長（熊谷裕人君）　高等学校等就学支援金の支給に関する法律の一部を改正する法律案を議題といたします。\r\n　本案に対する質疑は既に終局しております。\r\n　本案の修正について吉良さんから発言を求められておりますので、この際、これを許します。吉良よし子さん。",
      "url": "https://kokkai.ndl.go.jp/txt/122115104X00320260331/2"
    },
    {
      "date": "2026-03-31",
      "meeting": "文教科学委員会",
      "house": "参議院",
      "speaker": "熊谷裕人",
      "speech": "○委員長（熊谷裕人君）　ただいまの吉良さん提出の修正案は予算を伴うものでありますので、国会法第五十七条の三の規定により、内閣から本修正案に対する意見を聴取いたしたいと思います。松本文部科学大臣。",
      "url": "https://kokkai.ndl.go.jp/txt/122115104X00320260331/4"
    },
    {
      "date": "2026-03-31",
      "meeting": "文教科学委員会",
      "house": "参議院",
      "speaker": "熊谷裕人",
      "speech": "○委員長（熊谷裕人君）　これより原案及び修正案について討論に入ります。\r\n　御意見のある方は賛否を明らかにしてお述べ願います。",
      "url": "https://kokkai.ndl.go.jp/txt/122115104X00320260331/6"
    },
    {
      "date": "2026-03-31",
      "meeting": "文教科学委員会",
      "house": "参議院",
      "speaker": "熊谷裕人",
      "speech": "○委員長（熊谷裕人君）　他に御意見もないようですから、討論は終局したものと認めます。\r\n　これより高等学校等就学支援金の支給に関する法律の一部を改正する法律案について採決に入ります。\r\n　まず、吉良さん提出の修正案の採決を行います。\r\n　本修正案に賛成の方の挙手を願います。\r\n　　　〔賛成者挙手〕",
      "url": "https://kokkai.ndl.go.jp/txt/122115104X00320260331/8"
    },
    {
      "date": "2026-03-31",
      "meeting": "文教科学委員会",
      "house": "参議院",
      "speaker": "熊谷裕人",
      "speech": "○委員長（熊谷裕人君）　少数と認めます。よって、吉良さん提出の修正案は否決されました。\r\n　それでは、次に原案全部の採決を行います。\r\n　本案に賛成の方の挙手を願います。\r\n　　　〔賛成者挙手〕",
      "url": "https://kokkai.ndl.go.jp/txt/122115104X00320260331/9"
    },
    {
      "date": "2026-03-31",
      "meeting": "文教科学委員会",
      "house": "参議院",
      "speaker": "熊谷裕人",
      "speech": "○委員長（熊谷裕人君）　多数と認めます。よって、本案は多数をもって原案どおり可決すべきものと決定いたしました。\r\n　この際、古賀さんから発言を求められておりますので、これを許します。古賀千景さん。",
      "url": "https://kokkai.ndl.go.jp/txt/122115104X00320260331/10"
    },
    {
      "date": "2026-03-31",
      "meeting": "文教科学委員会",
      "house": "参議院",
      "speaker": "熊谷裕人",
      "speech": "○委員長（熊谷裕人君）　ただいま古賀さんから提出されました附帯決議案を議題とし、採決を行います。\r\n　本附帯決議案に賛成の方の挙手を願います。\r\n　　　〔賛成者挙手〕",
      "url": "https://kokkai.ndl.go.jp/txt/122115104X00320260331/12"
    },
    {
      "date": "2026-03-31",
      "meeting": "文教科学委員会",
      "house": "参議院",
      "speaker": "熊谷裕人",
      "speech": "○委員長（熊谷裕人君）　多数と認めます。よって、古賀さん提出の附帯決議案は多数をもって本委員会の決議とすることに決定いたしました。\r\n　ただいまの決議に対し、松本文部科学大臣から発言を求められておりますので、この際、これを許します。松本文部科学大臣。",
      "url": "https://kokkai.ndl.go.jp/txt/122115104X00320260331/13"
    },
    {
      "date": "2026-03-31",
      "meeting": "文教科学委員会",
      "house": "参議院",
      "speaker": "熊谷裕人",
      "speech": "○委員長（熊谷裕人君）　なお、審査報告書の作成につきましては、これを委員長に御一任願いたいと存じますが、御異議ございませんか。\r\n　　　〔「異議なし」と呼ぶ者あり〕",
      "url": "https://kokkai.ndl.go.jp/txt/122115104X00320260331/15"
    },
    {
      "date": "2026-03-31",
      "meeting": "文教科学委員会",
      "house": "参議院",
      "speaker": "熊谷裕人",
      "speech": "○委員長（熊谷裕人君）　御異議ないと認め、さよう決定いたします。\r\n　　　　─────────────",
      "url": "https://kokkai.ndl.go.jp/txt/122115104X00320260331/16"
    },
    {
      "date": "2026-03-31",
      "meeting": "文教科学委員会",
      "house": "参議院",
      "speaker": "熊谷裕人",
      "speech": "○委員長（熊谷裕人君）　次に、政府参考人の出席要求に関する件についてお諮りいたします。\r\n　公立義務教育諸学校の学級編制及び教職員定数の標準に関する法律の一部を改正する法律案の審査のため、本日の委員会に、理事会協議のとおり、財務省主計局次長中山光輝さん外五名を政府参考人として出席を求め、その説明を聴取することに御異議ございませんか。\r\n　　　〔「異議なし」と呼ぶ者あり〕",
      "url": "https://kokkai.ndl.go.jp/txt/122115104X00320260331/17"
    },
    {
      "date": "2026-03-31",
      "meeting": "文教科学委員会",
      "house": "参議院",
      "speaker": "熊谷裕人",
      "speech": "○委員長（熊谷裕人君）　御異議ないと認め、さよう決定いたします。\r\n　　　　─────────────",
      "url": "https://kokkai.ndl.go.jp/txt/122115104X00320260331/18"
    },
    {
      "date": "2026-03-31",
      "meeting": "文教科学委員会",
      "house": "参議院",
      "speaker": "熊谷裕人",
      "speech": "○委員長（熊谷裕人君）　公立義務教育諸学校の学級編制及び教職員定数の標準に関する法律の一部を改正する法律案を議題といたします。\r\n　本案の趣旨説明は既に聴取しておりますので、これより質疑に入ります。\r\n　質疑のある方は順次御発言願います。",
      "url": "https://kokkai.ndl.go.jp/txt/122115104X00320260331/19"
    },
    {
      "date": "2026-03-31",
      "meeting": "文教科学委員会",
      "house": "参議院",
      "speaker": "熊谷裕人",
      "speech": "○委員長（熊谷裕人君）　ただいまの件につきましては、後刻理事会において協議いたします。",
      "url": "https://kokkai.ndl.go.jp/txt/122115104X00320260331/36"
    },
    {
      "date": "2026-03-31",
      "meeting": "文教科学委員会",
      "house": "参議院",
      "speaker": "熊谷裕人",
      "speech": "○委員長（熊谷裕人君）　時間が来ておりますので、簡潔にお願いいたします。",
      "url": "https://kokkai.ndl.go.jp/txt/122115104X00320260331/81"
    },
    {
      "date": "2026-03-31",
      "meeting": "文教科学委員会",
      "house": "参議院",
      "speaker": "熊谷裕人",
      "speech": "○委員長（熊谷裕人君）　本日は子供たちにも傍聴していただきました。傍聴ありがとうございました。\r\n　せっかくなので、松本文科大臣から一言、子供たちに声を掛けていただければと思います。",
      "url": "https://kokkai.ndl.go.jp/txt/122115104X00320260331/103"
    },
    {
      "date": "2026-03-31",
      "meeting": "文教科学委員会",
      "house": "参議院",
      "speaker": "熊谷裕人",
      "speech": "○委員長（熊谷裕人君）　大臣、ありがとうございました。\r\n　午後一時に再開することとし、休憩いたします。\r\n　　　午後零時四分休憩\r\n　　　　　─────・─────\r\n　　　午後一時開会",
      "url": "https://kokkai.ndl.go.jp/txt/122115104X00320260331/105"
    },
    {
      "date": "2026-03-31",
      "meeting": "文教科学委員会",
      "house": "参議院",
      "speaker": "熊谷裕人",
      "speech": "○委員長（熊谷裕人君）　ただいまから文教科学委員会を再開いたします。\r\n　休憩前に引き続き、公立義務教育諸学校の学級編制及び教職員定数の標準に関する法律の一部を改正する法律案を議題とし、質疑を行います。\r\n　質疑のある方は順次御発言願います。",
      "url": "https://kokkai.ndl.go.jp/txt/122115104X00320260331/106"
    },
    {
      "date": "2026-03-31",
      "meeting": "文教科学委員会",
      "house": "参議院",
      "speaker": "熊谷裕人",
      "speech": "○委員長（熊谷裕人君）　時間が来ております。",
      "url": "https://kokkai.ndl.go.jp/txt/122115104X00320260331/180"
    },
    {
      "date": "2026-03-31",
      "meeting": "文教科学委員会",
      "house": "参議院",
      "speaker": "熊谷裕人",
      "speech": "○委員長（熊谷裕人君）　他に御発言もないようですから、質疑は終局したものと認めます。\r\n　本案の修正について吉良さんから発言を求められておりますので、この際、これを許します。吉良よし子さん。",
      "url": "https://kokkai.ndl.go.jp/txt/122115104X00320260331/182"
    },
    {
      "date": "2026-03-31",
      "meeting": "文教科学委員会",
      "house": "参議院",
      "speaker": "熊谷裕人",
      "speech": "○委員長（熊谷裕人君）　これより原案及び修正案について討論に入ります。──別に御意見もないようですから、これより直ちに公立義務教育諸学校の学級編制及び教職員定数の標準に関する法律の一部を改正する法律案について採決に入ります。\r\n　まず、吉良さん提出の修正案の採決を行います。\r\n　本修正案に賛成の方の挙手を願います。\r\n　　　〔賛成者挙手〕",
      "url": "https://kokkai.ndl.go.jp/txt/122115104X00320260331/184"
    },
    {
      "date": "2026-03-31",
      "meeting": "文教科学委員会",
      "house": "参議院",
      "speaker": "熊谷裕人",
      "speech": "○委員長（熊谷裕人君）　少数と認めます。よって、吉良さん提出の修正案は否決されました。\r\n　それでは、次に原案全部の採決を行います。\r\n　本案に賛成の方の挙手を願います。\r\n　　　〔賛成者挙手〕",
      "url": "https://kokkai.ndl.go.jp/txt/122115104X00320260331/185"
    },
    {
      "date": "2026-03-31",
      "meeting": "文教科学委員会",
      "house": "参議院",
      "speaker": "熊谷裕人",
      "speech": "○委員長（熊谷裕人君）　全会一致と認めます。よって、本案は全会一致をもって原案どおり可決すべきものと決定いたしました。\r\n　この際、古賀さんから発言を求められておりますので、これを許します。古賀千景さん。",
      "url": "https://kokkai.ndl.go.jp/txt/122115104X00320260331/186"
    },
    {
      "date": "2026-03-31",
      "meeting": "文教科学委員会",
      "house": "参議院",
      "speaker": "熊谷裕人",
      "speech": "○委員長（熊谷裕人君）　ただいま古賀さんから提出されました附帯決議案を議題とし、採決を行います。\r\n　本附帯決議案に賛成の方の挙手を願います。\r\n　　　〔賛成者挙手〕",
      "url": "https://kokkai.ndl.go.jp/txt/122115104X00320260331/188"
    },
    {
      "date": "2026-03-31",
      "meeting": "文教科学委員会",
      "house": "参議院",
      "speaker": "熊谷裕人",
      "speech": "○委員長（熊谷裕人君）　多数と認めます。よって、古賀さん提出の附帯決議案は多数をもって本委員会の決議とすることに決定いたしました。\r\n　ただいまの決議に対し、松本文部科学大臣から発言を求められておりますので、この際、これを許します。松本文部科学大臣。",
      "url": "https://kokkai.ndl.go.jp/txt/122115104X00320260331/189"
    },
    {
      "date": "2026-03-31",
      "meeting": "文教科学委員会",
      "house": "参議院",
      "speaker": "熊谷裕人",
      "speech": "○委員長（熊谷裕人君）　なお、審査報告書の作成につきましては、これを委員長に御一任願いたいと存じますが、御異議ございませんか。\r\n　　　〔「異議なし」と呼ぶ者あり〕",
      "url": "https://kokkai.ndl.go.jp/txt/122115104X00320260331/191"
    },
    {
      "date": "2026-03-31",
      "meeting": "文教科学委員会",
      "house": "参議院",
      "speaker": "熊谷裕人",
      "speech": "○委員長（熊谷裕人君）　御異議ないものと認め、さよう決定いたします。\r\n　本日はこれにて散会いたします。\r\n　　　午後二時三十八分散会",
      "url": "https://kokkai.ndl.go.jp/txt/122115104X00320260331/192"
    },
    {
      "date": "2026-03-26",
      "meeting": "文教科学委員会",
      "house": "参議院",
      "speaker": "熊谷裕人",
      "speech": "○委員長（熊谷裕人君）　ただいまから文教科学委員会を開会いたします。\r\n　この際、松本文部科学大臣から発言を求められておりますので、これを許します。松本文部科学大臣。",
      "url": "https://kokkai.ndl.go.jp/txt/122115104X00220260326/1"
    },
    {
      "date": "2026-03-26",
      "meeting": "文教科学委員会",
      "house": "参議院",
      "speaker": "熊谷裕人",
      "speech": "○委員長（熊谷裕人君）　次に、政府参考人の出席要求に関する件についてお諮りいたします。\r\n　高等学校等就学支援金の支給に関する法律の一部を改正する法律案の審査のため、本日の委員会に、理事会協議のとおり、文部科学省大臣官房長茂里毅さん外六名を政府参考人として出席を求め、その説明を聴取することに御異議ございませんか。\r\n　　　〔「異議なし」と呼ぶ者あり〕",
      "url": "https://kokkai.ndl.go.jp/txt/122115104X00220260326/3"
    },
    {
      "date": "2026-03-26",
      "meeting": "文教科学委員会",
      "house": "参議院",
      "speaker": "熊谷裕人",
      "speech": "○委員長（熊谷裕人君）　異議ないと認め、さよう決定いたします。\r\n　　　　─────────────",
      "url": "https://kokkai.ndl.go.jp/txt/122115104X00220260326/4"
    },
    {
      "date": "2026-03-26",
      "meeting": "文教科学委員会",
      "house": "参議院",
      "speaker": "熊谷裕人",
      "speech": "○委員長（熊谷裕人君）　高等学校等就学支援金の支給に関する法律の一部を改正する法律案を議題といたします。\r\n　本案の趣旨説明は既に聴取しておりますので、これより質疑に入ります。\r\n　質疑のある方は順次御発言願います。",
      "url": "https://kokkai.ndl.go.jp/txt/122115104X00220260326/5"
    },
    {
      "date": "2026-03-26",
      "meeting": "文教科学委員会",
      "house": "参議院",
      "speaker": "熊谷裕人",
      "speech": "○委員長（熊谷裕人君）　申合せの時間が来ておりますので、簡潔にお願いいたします。",
      "url": "https://kokkai.ndl.go.jp/txt/122115104X00220260326/89"
    },
    {
      "date": "2026-03-26",
      "meeting": "文教科学委員会",
      "house": "参議院",
      "speaker": "熊谷裕人",
      "speech": "○委員長（熊谷裕人君）　午後一時二十五分に再開することとし、休憩いたします。\r\n　　　午後零時二十八分休憩\r\n　　　　　─────・─────\r\n　　　午後一時二十五分開会",
      "url": "https://kokkai.ndl.go.jp/txt/122115104X00220260326/121"
    },
    {
      "date": "2026-03-26",
      "meeting": "文教科学委員会",
      "house": "参議院",
      "speaker": "熊谷裕人",
      "speech": "○委員長（熊谷裕人君）　ただいまから文教科学委員会を再開いたします。\r\n　委員の異動について御報告いたします。\r\n　本日、上野通子さんが委員を辞任され、その補欠としてかまやち敏さんが選任されました。\r\n　　　　─────────────",
      "url": "https://kokkai.ndl.go.jp/txt/122115104X00220260326/122"
    },
    {
      "date": "2026-03-26",
      "meeting": "文教科学委員会",
      "house": "参議院",
      "speaker": "熊谷裕人",
      "speech": "○委員長（熊谷裕人君）　休憩前に引き続き、高等学校等就学支援金の支給に関する法律の一部を改正する法律案を議題とし、質疑を行います。\r\n　質疑のある方は順次御発言願います。",
      "url": "https://kokkai.ndl.go.jp/txt/122115104X00220260326/123"
    },
    {
      "date": "2026-03-26",
      "meeting": "文教科学委員会",
      "house": "参議院",
      "speaker": "熊谷裕人",
      "speech": "○委員長（熊谷裕人君）　他に御発言もないようですから、質疑は終局したものと認めます。\r\n　　　　─────────────",
      "url": "https://kokkai.ndl.go.jp/txt/122115104X00220260326/190"
    },
    {
      "date": "2026-03-26",
      "meeting": "文教科学委員会",
      "house": "参議院",
      "speaker": "熊谷裕人",
      "speech": "○委員長（熊谷裕人君）　次に、公立義務教育諸学校の学級編制及び教職員定数の標準に関する法律の一部を改正する法律案を議題といたします。\r\n　政府から趣旨説明を聴取いたします。松本文部科学大臣。",
      "url": "https://kokkai.ndl.go.jp/txt/122115104X00220260326/191"
    },
    {
      "date": "2026-03-26",
      "meeting": "文教科学委員会",
      "house": "参議院",
      "speaker": "熊谷裕人",
      "speech": "○委員長（熊谷裕人君）　以上で趣旨説明の聴取は終わりました。\r\n　本案に対する質疑は後日に譲ることとし、本日はこれにて散会いたします。\r\n　　　午後三時十六分散会",
      "url": "https://kokkai.ndl.go.jp/txt/122115104X00220260326/193"
    },
    {
      "date": "2026-03-24",
      "meeting": "文教科学委員会",
      "house": "参議院",
      "speaker": "熊谷裕人",
      "speech": "○委員長（熊谷裕人君）　ただいまから文教科学委員会を開会いたします。\r\n　委員の異動について御報告いたします。\r\n　昨日までに、ラサール石井さんが委員を辞任され、その補欠として勝部賢志さんが選任されました。\r\n　　　　─────────────",
      "url": "https://kokkai.ndl.go.jp/txt/122115104X00120260324/1"
    },
    {
      "date": "2026-03-24",
      "meeting": "文教科学委員会",
      "house": "参議院",
      "speaker": "熊谷裕人",
      "speech": "○委員長（熊谷裕人君）　国政調査に関する件についてお諮りいたします。\r\n　本委員会は、今期国会におきましても、教育、文化、スポーツ、学術及び科学技術に関する調査を行いたいと存じますが、御異議ございませんですか。\r\n　　　〔「異議なし」と呼ぶ者あり〕",
      "url": "https://kokkai.ndl.go.jp/txt/122115104X00120260324/2"
    },
    {
      "date": "2026-03-24",
      "meeting": "文教科学委員会",
      "house": "参議院",
      "speaker": "熊谷裕人",
      "speech": "○委員長（熊谷裕人君）　御異議ないと認め、さよう決定いたします。\r\n　　　　─────────────",
      "url": "https://kokkai.ndl.go.jp/txt/122115104X00120260324/3"
    },
    {
      "date": "2026-03-24",
      "meeting": "文教科学委員会",
      "house": "参議院",
      "speaker": "熊谷裕人",
      "speech": "○委員長（熊谷裕人君）　教育、文化、スポーツ、学術及び科学技術に関する調査を議題といたします。\r\n　まず、文教科学行政の基本施策について、松本文部科学大臣から所信を聴取いたします。松本文部科学大臣。",
      "url": "https://kokkai.ndl.go.jp/txt/122115104X00120260324/4"
    },
    {
      "date": "2026-03-24",
      "meeting": "文教科学委員会",
      "house": "参議院",
      "speaker": "熊谷裕人",
      "speech": "○委員長（熊谷裕人君）　次に、令和八年度文部科学省関係予算について、中村文部科学副大臣から説明を聴取いたします。中村文部科学副大臣。",
      "url": "https://kokkai.ndl.go.jp/txt/122115104X00120260324/6"
    },
    {
      "date": "2026-03-24",
      "meeting": "文教科学委員会",
      "house": "参議院",
      "speaker": "熊谷裕人",
      "speech": "○委員長（熊谷裕人君）　以上で所信及び予算説明の聴取は終わりました。\r\n　本件に対する質疑は後日に譲ることといたします。\r\n　この際、小林文部科学副大臣、清水文部科学大臣政務官、福田文部科学大臣政務官から発言を求められておりますので、順次これを許します。小林文部科学副大臣。",
      "url": "https://kokkai.ndl.go.jp/txt/122115104X00120260324/8"
    },
    {
      "date": "2026-03-24",
      "meeting": "文教科学委員会",
      "house": "参議院",
      "speaker": "熊谷裕人",
      "speech": "○委員長（熊谷裕人君）　清水文部科学大臣政務官。",
      "url": "https://kokkai.ndl.go.jp/txt/122115104X00120260324/10"
    },
    {
      "date": "2026-03-24",
      "meeting": "文教科学委員会",
      "house": "参議院",
      "speaker": "熊谷裕人",
      "speech": "○委員長（熊谷裕人君）　福田文部科学大臣政務官。",
      "url": "https://kokkai.ndl.go.jp/txt/122115104X00120260324/12"
    },
    {
      "date": "2026-03-24",
      "meeting": "文教科学委員会",
      "house": "参議院",
      "speaker": "熊谷裕人",
      "speech": "○委員長（熊谷裕人君）　どうぞ御退席、御移動をお願いします。\r\n　　　　─────────────",
      "url": "https://kokkai.ndl.go.jp/txt/122115104X00120260324/14"
    },
    {
      "date": "2026-03-24",
      "meeting": "文教科学委員会",
      "house": "参議院",
      "speaker": "熊谷裕人",
      "speech": "○委員長（熊谷裕人君）　次に、高等学校等就学支援金の支給に関する法律の一部を改正する法律案を議題といたします。\r\n　政府から趣旨説明を聴取いたします。松本文部科学大臣。",
      "url": "https://kokkai.ndl.go.jp/txt/122115104X00120260324/15"
    },
    {
      "date": "2026-03-24",
      "meeting": "文教科学委員会",
      "house": "参議院",
      "speaker": "熊谷裕人",
      "speech": "○委員長（熊谷裕人君）　以上で趣旨説明の聴取は終わりました。\r\n　本案に対する質疑は後日に譲ることとし、本日はこれにて散会いたします。\r\n　　　午後一時四十分散会",
      "url": "https://kokkai.ndl.go.jp/txt/122115104X00120260324/17"
    },
    {
      "date": "2026-01-23",
      "meeting": "文教科学委員会",
      "house": "参議院",
      "speaker": "熊谷裕人",
      "speech": "○委員長（熊谷裕人君）　ただいまから文教科学委員会を開会いたします。\r\n　国政調査及び継続調査要求に関する件についてお諮りいたします。\r\n　本委員会は、従来どおり教育、文化、スポーツ、学術及び科学技術に関する調査を行うこととし、今期国会閉会の場合においても継続して調査を行うため、本件の継続調査要求書を議長に提出いたしたいと存じますが、御異議ございませんでしょうか。\r\n　　　〔「異議なし」と呼ぶ者あり〕",
      "url": "https://kokkai.ndl.go.jp/txt/122015104X00120260123/1"
    },
    {
      "date": "2026-01-23",
      "meeting": "文教科学委員会",
      "house": "参議院",
      "speaker": "熊谷裕人",
      "speech": "○委員長（熊谷裕人君）　御異議ないと認め、さよう決定いたします。\r\n　なお、要求書の作成につきましては委員長に御一任願いたいと存じますが、御異議ございませんでしょうか。\r\n　　　〔「異議なし」と呼ぶ者あり〕",
      "url": "https://kokkai.ndl.go.jp/txt/122015104X00120260123/2"
    },
    {
      "date": "2026-01-23",
      "meeting": "文教科学委員会",
      "house": "参議院",
      "speaker": "熊谷裕人",
      "speech": "○委員長（熊谷裕人君）　御異議ないと認め、さよう決定いたします。\r\n　本日はこれにて散会いたします。\r\n　　　午前十時二十一分散会",
      "url": "https://kokkai.ndl.go.jp/txt/122015104X00120260123/3"
    },
    {
      "date": "2025-12-17",
      "meeting": "文教科学委員会",
      "house": "参議院",
      "speaker": "熊谷裕人",
      "speech": "○委員長（熊谷裕人君）　ただいまから文教科学委員会を開会いたします。\r\n　委員の異動について御報告いたします。\r\n　昨日までに、福島みずほさん、竹内真二さん及び東野秀樹さんが委員を辞任され、その補欠としてラサール石井さん、谷合正明さん及び末松信介さんが選任されました。\r\n　　　　─────────────",
      "url": "https://kokkai.ndl.go.jp/txt/121915104X00520251217/1"
    },
    {
      "date": "2025-12-17",
      "meeting": "文教科学委員会",
      "house": "参議院",
      "speaker": "熊谷裕人",
      "speech": "○委員長（熊谷裕人君）　これより請願の審査を行います。\r\n　第五三号教職員が教育に専念できる環境の整備に関する請願外五十二件を議題といたします。\r\n　これらの請願につきましては、理事会において協議の結果、いずれも保留とすることになりました。\r\n　以上のとおり決定することに御異議ございませんか。\r\n　　　〔「異議なし」と呼ぶ者あり〕",
      "url": "https://kokkai.ndl.go.jp/txt/121915104X00520251217/2"
    },
    {
      "date": "2025-12-17",
      "meeting": "文教科学委員会",
      "house": "参議院",
      "speaker": "熊谷裕人",
      "speech": "○委員長（熊谷裕人君）　御異議なしと認めます。よって、さよう決定いたしました。\r\n　　　　─────────────",
      "url": "https://kokkai.ndl.go.jp/txt/121915104X00520251217/3"
    },
    {
      "date": "2025-12-17",
      "meeting": "文教科学委員会",
      "house": "参議院",
      "speaker": "熊谷裕人",
      "speech": "○委員長（熊谷裕人君）　継続調査要求に関する件についてお諮りいたします。\r\n　教育、文化、スポーツ、学術及び科学技術に関する調査につきましては、閉会中もなお調査を継続することとし、本件の継続調査要求書を議長に提出いたしたいと存じますが、御異議ございませんでしょうか。\r\n　　　〔「異議なし」と呼ぶ者あり〕",
      "url": "https://kokkai.ndl.go.jp/txt/121915104X00520251217/4"
    },
    {
      "date": "2025-12-17",
      "meeting": "文教科学委員会",
      "house": "参議院",
      "speaker": "熊谷裕人",
      "speech": "○委員長（熊谷裕人君）　御異議ないと認め、さよう決定いたします。\r\n　なお、要求書の作成につきましては委員長に御一任願いたいと存じますが、御異議ございませんでしょうか。\r\n　　　〔「異議なし」と呼ぶ者あり〕",
      "url": "https://kokkai.ndl.go.jp/txt/121915104X00520251217/5"
    },
    {
      "date": "2025-12-17",
      "meeting": "文教科学委員会",
      "house": "参議院",
      "speaker": "熊谷裕人",
      "speech": "○委員長（熊谷裕人君）　御異議ないと認め、さよう決定いたします。\r\n　　　　─────────────",
      "url": "https://kokkai.ndl.go.jp/txt/121915104X00520251217/6"
    },
    {
      "date": "2025-12-17",
      "meeting": "文教科学委員会",
      "house": "参議院",
      "speaker": "熊谷裕人",
      "speech": "○委員長（熊谷裕人君）　委員派遣に関する件についてお諮りいたします。\r\n　閉会中の委員派遣につきましては、その取扱いを委員長に御一任願いたいと存じますが、御異議ございませんでしょうか。\r\n　　　〔「異議なし」と呼ぶ者あり〕",
      "url": "https://kokkai.ndl.go.jp/txt/121915104X00520251217/7"
    },
    {
      "date": "2025-12-17",
      "meeting": "文教科学委員会",
      "house": "参議院",
      "speaker": "熊谷裕人",
      "speech": "○委員長（熊谷裕人君）　御異議ないと認め、さよう取り計らいます。\r\n　本日はこれにて散会いたします。\r\n　　　午前十時一分散会",
      "url": "https://kokkai.ndl.go.jp/txt/121915104X00520251217/8"
    },
    {
      "date": "2025-12-04",
      "meeting": "文教科学委員会",
      "house": "参議院",
      "speaker": "熊谷裕人",
      "speech": "○委員長（熊谷裕人君）　ただいまから文教科学委員会を開会いたします。\r\n　委員の異動について御報告いたします。\r\n　昨日までに、東野秀樹さん、ラサール石井さん及び谷合正明さんが委員を辞任され、その補欠として片山さつきさん、福島みずほさん及び竹内真二さんが選任されました。\r\n　　　　─────────────",
      "url": "https://kokkai.ndl.go.jp/txt/121915104X00420251204/1"
    },
    {
      "date": "2025-12-04",
      "meeting": "文教科学委員会",
      "house": "参議院",
      "speaker": "熊谷裕人",
      "speech": "○委員長（熊谷裕人君）　政府参考人の出席要求に関する件についてお諮りいたします。\r\n　教育、文化、スポーツ、学術及び科学技術に関する調査のため、本日の委員会に、理事会協議のとおり、内閣府科学技術・イノベーション推進事務局審議官原克彦さん外九名を政府参考人として出席を求め、その説明を聴取することに御異議ございませんか。\r\n　　　〔「異議なし」と呼ぶ者あり〕",
      "url": "https://kokkai.ndl.go.jp/txt/121915104X00420251204/2"
    },
    {
      "date": "2025-12-04",
      "meeting": "文教科学委員会",
      "house": "参議院",
      "speaker": "熊谷裕人",
      "speech": "○委員長（熊谷裕人君）　異議ないと認め、さよう決定いたします。\r\n　　　　─────────────",
      "url": "https://kokkai.ndl.go.jp/txt/121915104X00420251204/3"
    },
    {
      "date": "2025-12-04",
      "meeting": "文教科学委員会",
      "house": "参議院",
      "speaker": "熊谷裕人",
      "speech": "○委員長（熊谷裕人君）　教育、文化、スポーツ、学術及び科学技術に関する調査を議題とし、質疑を行います。\r\n　質疑のある方は順次御発言願います。",
      "url": "https://kokkai.ndl.go.jp/txt/121915104X00420251204/4"
    },
    {
      "date": "2025-12-04",
      "meeting": "文教科学委員会",
      "house": "参議院",
      "speaker": "熊谷裕人",
      "speech": "○委員長（熊谷裕人君）　この際、委員の異動について御報告いたします。\r\n　本日、末松信介さんが委員を辞任され、その補欠として東野秀樹さんが選任されました。\r\n　　　　─────────────",
      "url": "https://kokkai.ndl.go.jp/txt/121915104X00420251204/42"
    },
    {
      "date": "2025-12-04",
      "meeting": "文教科学委員会",
      "house": "参議院",
      "speaker": "熊谷裕人",
      "speech": "○委員長（熊谷裕人君）　本日の調査はこの程度にとどめ、これにて散会いたします。\r\n　　　午後零時八分散会",
      "url": "https://kokkai.ndl.go.jp/txt/121915104X00420251204/95"
    },
    {
      "date": "2025-12-03",
      "meeting": "本会議",
      "house": "参議院",
      "speaker": "熊谷裕人",
      "speech": "○熊谷裕人君　ただいま議題となりました本法律案につきまして、文教科学委員会における審査の経過と結果を御報告申し上げます。\r\n　本法律案は、衆議院文部科学委員長の提出によるものであり、令和八年に開催される愛知・名古屋アジア競技大会及び愛知・名古屋アジアパラ競技大会が大規模かつ国家的に重要なスポーツの競技会であることに鑑み、最近における社会経済情勢の急激な変化に対して経費の削減等を図りつつ的確に対応するとともに、これらの競技大会の円滑かつ安全な実施を確保する観点から施設の警備、暑熱に関する対策等に万全を期するために、必要な特別措置について定めようとするものであります。\r\n　委員会におきまして、過去に我が国で開催された国際スポーツ大会等に係る特別措置法との比較、組織委員会及び開催自治体の説明責任等について質疑が行われましたが、その詳細は会議録によって御承知願いたいと存じます。\r\n　質疑を終局し、採決の結果、本法律案は多数をもって原案どおり可決すべきものと決定いたしました。\r\n　以上、御報告申し上げます。（拍手）\r\n　　　　─────────────",
      "url": "https://kokkai.ndl.go.jp/txt/121915254X00720251203/45"
    },
    {
      "date": "2025-12-02",
      "meeting": "文教科学委員会",
      "house": "参議院",
      "speaker": "熊谷裕人",
      "speech": "○委員長（熊谷裕人君）　ただいまから文教科学委員会を開会いたします。\r\n　委員の異動について御報告いたします。\r\n　昨日までに、宮崎勝さん及び片山さつきさんが委員を辞任され、その補欠として谷合正明さん及び東野秀樹さんが選任されました。\r\n　　　　─────────────",
      "url": "https://kokkai.ndl.go.jp/txt/121915104X00320251202/1"
    },
    {
      "date": "2025-12-02",
      "meeting": "文教科学委員会",
      "house": "参議院",
      "speaker": "熊谷裕人",
      "speech": "○委員長（熊谷裕人君）　政府参考人の出席要求に関する件についてお諮りいたします。\r\n　愛知・名古屋アジア競技大会及び愛知・名古屋アジアパラ競技大会に関する特別措置法案の審査のため、本日の委員会に、理事会協議のとおり、スポーツ庁次長浅野敦行さんを政府参考人として出席を求め、その説明を聴取することに御異議ございませんか。\r\n　　　〔「異議なし」と呼ぶ者あり〕",
      "url": "https://kokkai.ndl.go.jp/txt/121915104X00320251202/2"
    },
    {
      "date": "2025-12-02",
      "meeting": "文教科学委員会",
      "house": "参議院",
      "speaker": "熊谷裕人",
      "speech": "○委員長（熊谷裕人君）　御異議ないと認め、さよう決定いたします。\r\n　　　　─────────────",
      "url": "https://kokkai.ndl.go.jp/txt/121915104X00320251202/3"
    },
    {
      "date": "2025-12-02",
      "meeting": "文教科学委員会",
      "house": "参議院",
      "speaker": "熊谷裕人",
      "speech": "○委員長（熊谷裕人君）　愛知・名古屋アジア競技大会及び愛知・名古屋アジアパラ競技大会に関する特別措置法案を議題といたします。\r\n　提出者の衆議院文部科学委員長斎藤洋明さんから趣旨説明を聴取いたします。斎藤衆議院文部科学委員長。お願いします。",
      "url": "https://kokkai.ndl.go.jp/txt/121915104X00320251202/4"
    },
    {
      "date": "2025-12-02",
      "meeting": "文教科学委員会",
      "house": "参議院",
      "speaker": "熊谷裕人",
      "speech": "○委員長（熊谷裕人君）　以上で趣旨説明の聴取は終わりました。\r\n　これより質疑に入ります。\r\n　質疑のある方は順次御発言願います。",
      "url": "https://kokkai.ndl.go.jp/txt/121915104X00320251202/6"
    },
    {
      "date": "2025-12-02",
      "meeting": "文教科学委員会",
      "house": "参議院",
      "speaker": "熊谷裕人",
      "speech": "○委員長（熊谷裕人君）　他に御発言もないようですから、質疑は終局したものと認めます。\r\n　これより討論に入ります。──別に御意見もないようですから、これより直ちに採決に入ります。\r\n　愛知・名古屋アジア競技大会及び愛知・名古屋アジアパラ競技大会に関する特別措置法案に賛成の方の挙手を願います。\r\n　　　〔賛成者挙手〕",
      "url": "https://kokkai.ndl.go.jp/txt/121915104X00320251202/19"
    },
    {
      "date": "2025-12-02",
      "meeting": "文教科学委員会",
      "house": "参議院",
      "speaker": "熊谷裕人",
      "speech": "○委員長（熊谷裕人君）　多数と認めます。よって、本案は多数をもって原案どおり可決すべきものと決定いたしました。\r\n　なお、審査報告書の作成につきましては、これを委員長に御一任願いたいと存じますが、御異議ございませんでしょうか。\r\n　　　〔「異議なし」と呼ぶ者あり〕",
      "url": "https://kokkai.ndl.go.jp/txt/121915104X00320251202/20"
    },
    {
      "date": "2025-12-02",
      "meeting": "文教科学委員会",
      "house": "参議院",
      "speaker": "熊谷裕人",
      "speech": "○委員長（熊谷裕人君）　御異議ないと認め、さよう決定いたします。\r\n　本日はこれにて散会いたします。\r\n　　　午前十時二十二分散会",
      "url": "https://kokkai.ndl.go.jp/txt/121915104X00320251202/21"
    },
    {
      "date": "2025-11-20",
      "meeting": "文教科学委員会",
      "house": "参議院",
      "speaker": "熊谷裕人",
      "speech": "○委員長（熊谷裕人君）　ただいまから文教科学委員会を開会いたします。\r\n　政府参考人の出席要求に関する件についてお諮りいたします。\r\n　教育、文化、スポーツ、学術及び科学技術に関する調査のため、本日の委員会に、理事会協議のとおり、こども家庭庁長官官房審議官竹林悟史さん外十三名を政府参考人として出席を求め、その説明を聴取することに御異議ございませんか。\r\n　　　〔「異議なし」と呼ぶ者あり〕",
      "url": "https://kokkai.ndl.go.jp/txt/121915104X00220251120/1"
    },
    {
      "date": "2025-11-20",
      "meeting": "文教科学委員会",
      "house": "参議院",
      "speaker": "熊谷裕人",
      "speech": "○委員長（熊谷裕人君）　異議なしと認め、さよう決定いたします。\r\n　　　　─────────────",
      "url": "https://kokkai.ndl.go.jp/txt/121915104X00220251120/2"
    },
    {
      "date": "2025-11-20",
      "meeting": "文教科学委員会",
      "house": "参議院",
      "speaker": "熊谷裕人",
      "speech": "○委員長（熊谷裕人君）　教育、文化、スポーツ、学術及び科学技術に関する調査を議題とし、質疑を行います。\r\n　質疑のある方は順次御発言願います。",
      "url": "https://kokkai.ndl.go.jp/txt/121915104X00220251120/3"
    },
    {
      "date": "2025-11-20",
      "meeting": "文教科学委員会",
      "house": "参議院",
      "speaker": "熊谷裕人",
      "speech": "○委員長（熊谷裕人君）　この際、午後一時に再開することとし、休憩いたします。\r\n　　　午前十一時四十八分休憩\r\n　　　　　─────・─────\r\n　　　午後一時開会",
      "url": "https://kokkai.ndl.go.jp/txt/121915104X00220251120/112"
    },
    {
      "date": "2025-11-20",
      "meeting": "文教科学委員会",
      "house": "参議院",
      "speaker": "熊谷裕人",
      "speech": "○委員長（熊谷裕人君）　ただいまから文教科学委員会を再開いたします。\r\n　休憩前に引き続き、教育、文化、スポーツ、学術及び科学技術に関する調査を議題とし、質疑を行います。\r\n　質疑のある方は順次御発言お願いいたします。",
      "url": "https://kokkai.ndl.go.jp/txt/121915104X00220251120/113"
    },
    {
      "date": "2025-11-20",
      "meeting": "文教科学委員会",
      "house": "参議院",
      "speaker": "熊谷裕人",
      "speech": "○委員長（熊谷裕人君）　御答弁できるようでしたらお願いいたします。",
      "url": "https://kokkai.ndl.go.jp/txt/121915104X00220251120/166"
    },
    {
      "date": "2025-11-20",
      "meeting": "文教科学委員会",
      "house": "参議院",
      "speaker": "熊谷裕人",
      "speech": "○委員長（熊谷裕人君）　この際、委員の異動について御報告いたします。\r\n　本日、谷合正明さんが委員を辞任され、その補欠として宮崎勝さんが選任されました。\r\n　　　　─────────────",
      "url": "https://kokkai.ndl.go.jp/txt/121915104X00220251120/213"
    },
    {
      "date": "2025-11-20",
      "meeting": "文教科学委員会",
      "house": "参議院",
      "speaker": "熊谷裕人",
      "speech": "○委員長（熊谷裕人君）　その点お答えください。",
      "url": "https://kokkai.ndl.go.jp/txt/121915104X00220251120/225"
    },
    {
      "date": "2025-11-20",
      "meeting": "文教科学委員会",
      "house": "参議院",
      "speaker": "熊谷裕人",
      "speech": "○委員長（熊谷裕人君）　本日の調査はこの程度にとどめ、これにて散会いたします。\r\n　　　午後三時四十六分散会",
      "url": "https://kokkai.ndl.go.jp/txt/121915104X00220251120/248"
    },
    {
      "date": "2025-11-18",
      "meeting": "文教科学委員会",
      "house": "参議院",
      "speaker": "熊谷裕人",
      "speech": "○委員長（熊谷裕人君）　ただいまから文教科学委員会を開会いたします。\r\n　議事に先立ちまして、一言御挨拶申し上げます。\r\n　去る十月二十一日の本会議におきまして文教科学委員長に選任されました熊谷裕人でございます。\r\n　委員各位の御指導、御協力を賜りまして、公正かつ円満な委員会運営に努めてまいりたいと存じます。何とぞどうぞよろしくお願いいたします。（拍手）\r\n　　　　─────────────",
      "url": "https://kokkai.ndl.go.jp/txt/121915104X00120251118/1"
    },
    {
      "date": "2025-11-18",
      "meeting": "文教科学委員会",
      "house": "参議院",
      "speaker": "熊谷裕人",
      "speech": "○委員長（熊谷裕人君）　委員の異動について御報告いたします。\r\n　昨日までに、小林孝一郎さん、見坂茂範さん、臼井正一さん、平木大作さん、堂込麻紀子さん、水岡俊一さん、森ゆうこさん及び勝部賢志さんが委員を辞任され、その補欠として清水真人さん、宮本和宏さん、水野孝一さん、ラサール石井さん、古賀千景さん、谷合正明さん、片山さつきさん及び私、熊谷裕人が選任されました。\r\n　　　　─────────────",
      "url": "https://kokkai.ndl.go.jp/txt/121915104X00120251118/2"
    },
    {
      "date": "2025-11-18",
      "meeting": "文教科学委員会",
      "house": "参議院",
      "speaker": "熊谷裕人",
      "speech": "○委員長（熊谷裕人君）　理事の補欠選任についてお諮りいたします。\r\n　委員の異動に伴い現在理事が四名欠員となっておりますので、その補欠選任を行いたいと存じます。\r\n　理事の選任につきましては、先例により、委員長の指名に御一任願いたいと存じますが、御異議ございませんでしょうか。\r\n　　　〔「異議なし」と呼ぶ者あり〕",
      "url": "https://kokkai.ndl.go.jp/txt/121915104X00120251118/3"
    },
    {
      "date": "2025-11-18",
      "meeting": "文教科学委員会",
      "house": "参議院",
      "speaker": "熊谷裕人",
      "speech": "○委員長（熊谷裕人君）　御異議なしと認めます。\r\n　それでは、理事に赤松健さん、古賀千景さん、伊藤孝恵さん、金子道仁さんを指名いたします。\r\n　　　　─────────────",
      "url": "https://kokkai.ndl.go.jp/txt/121915104X00120251118/4"
    },
    {
      "date": "2025-11-18",
      "meeting": "文教科学委員会",
      "house": "参議院",
      "speaker": "熊谷裕人",
      "speech": "○委員長（熊谷裕人君）　国政調査に関する件についてお諮りいたします。\r\n　本委員会は、今期国会におきましても、教育、文化、スポーツ、学術及び科学技術に関する調査を行いたいと存じますが、御異議ございませんか。\r\n　　　〔「異議なし」と呼ぶ者あり〕",
      "url": "https://kokkai.ndl.go.jp/txt/121915104X00120251118/5"
    },
    {
      "date": "2025-11-18",
      "meeting": "文教科学委員会",
      "house": "参議院",
      "speaker": "熊谷裕人",
      "speech": "○委員長（熊谷裕人君）　御異議ないと認め、さよう決定いたします。\r\n　　　　─────────────",
      "url": "https://kokkai.ndl.go.jp/txt/121915104X00120251118/6"
    },
    {
      "date": "2025-11-18",
      "meeting": "文教科学委員会",
      "house": "参議院",
      "speaker": "熊谷裕人",
      "speech": "○委員長（熊谷裕人君）　この際、松本文部科学大臣、中村文部科学副大臣、小林文部科学副大臣、清水文部科学大臣政務官、福田文部科学大臣政務官から発言を求められておりますので、順次これを許します。松本洋平文部科学大臣。",
      "url": "https://kokkai.ndl.go.jp/txt/121915104X00120251118/7"
    },
    {
      "date": "2025-11-18",
      "meeting": "文教科学委員会",
      "house": "参議院",
      "speaker": "熊谷裕人",
      "speech": "○委員長（熊谷裕人君）　中村裕之文部科学副大臣。",
      "url": "https://kokkai.ndl.go.jp/txt/121915104X00120251118/9"
    },
    {
      "date": "2025-11-18",
      "meeting": "文教科学委員会",
      "house": "参議院",
      "speaker": "熊谷裕人",
      "speech": "○委員長（熊谷裕人君）　小林茂樹文部科学副大臣。",
      "url": "https://kokkai.ndl.go.jp/txt/121915104X00120251118/11"
    },
    {
      "date": "2025-11-18",
      "meeting": "文教科学委員会",
      "house": "参議院",
      "speaker": "熊谷裕人",
      "speech": "○委員長（熊谷裕人君）　清水真人文部科学大臣政務官。",
      "url": "https://kokkai.ndl.go.jp/txt/121915104X00120251118/13"
    },
    {
      "date": "2025-11-18",
      "meeting": "文教科学委員会",
      "house": "参議院",
      "speaker": "熊谷裕人",
      "speech": "○委員長（熊谷裕人君）　福田かおる文部科学大臣政務官。",
      "url": "https://kokkai.ndl.go.jp/txt/121915104X00120251118/15"
    },
    {
      "date": "2025-11-18",
      "meeting": "文教科学委員会",
      "house": "参議院",
      "speaker": "熊谷裕人",
      "speech": "○委員長（熊谷裕人君）　本日はこれにて散会いたします。\r\n　　　午前十時十九分散会",
      "url": "https://kokkai.ndl.go.jp/txt/121915104X00120251118/17"
    },
    {
      "date": "2025-06-21",
      "meeting": "議院運営委員会",
      "house": "参議院",
      "speaker": "熊谷裕人",
      "speech": "○熊谷裕人君　立憲民主・社民・無所属の熊谷でございます。\r\n　私の方から意見表明をさせていただきます。\r\n　私たち参議院議員、国会議員は、法治国家における唯一無二の立法権を国民、有権者から委ねられた立法機関の者になりますし、国権の最高機関に身を置く者であります。与えられた有限の時間の中で法案審議を行い、熟議を重ね、結論を出すために努力を重ねてきたその行為は、ひとえに、自らが正しいと確信を持ち、結論を議決し、自らの国権の最高機関に身を置く者としての責任を持って下すためなのであり、この立法における議決権こそが立法機関、すなわち国権の最高機関である国会の至高の機能であるというふうに思いますし、それが我々の職責なのだと私は考えております。議決という権能がなければ、立法に関する単なる意見表明者あるいは参考人でしかなく、国会議員としての権能を奪うことはあってはならないと私は考えております。\r\n　法案が衆議院から参議院に送付され、本会議で質疑を行い、財政金融委員会に付託されたわけでありますが、財政金融委員会で質疑を行った上で採決をすることが当然のことであり、国会の役割、権能を考えても、採決をしないなどということがあってはならないと考えております。財政金融委員会の場において、自民党の議員からも採決はするべきだとの発言があり、議論を続けるべきだと私は思っておりました。\r\n　そもそも、本日の財政金融委員会の質疑時間は、与党の側から二時間という提案があったものであります。その提案を受けて委員会が開かれ、そして採決をするべきという主張を我々は理事会の場でも主張し続けさせていただきました。しかし、理事会の場で議論の末に採決に至ることができなかったとして、三宅財政委員長は委員会の散会を職権で宣言をしてしまいました。\r\n　委員会の審議を続けて採決に至る道を探るのが本来の委員長の職責ではないかと私は思っております。したがって、一方的に職権で委員会の散会を宣言した三宅財政委員長には、委員長の職責を自ら放棄したと同じことであり、私は、この委員長の解任決議案を、委員会での審査省略をし、本会議で議案として是非扱っていただきたいという主張をさせていただき、会派としての意見表明とさせていただきたいと思います。",
      "url": "https://kokkai.ndl.go.jp/txt/121714024X03120250621/4"
    },
    {
      "date": "2025-06-21",
      "meeting": "財政金融委員会",
      "house": "参議院",
      "speaker": "熊谷裕人",
      "speech": "○熊谷裕人君　立憲民主・社民・無所属の熊谷裕人です。\r\n　何かいつもと雰囲気が違いまして、財務大臣や日銀総裁に質問するよりか、私、今日緊張しております。是非、答弁者の皆様にも真摯な御答弁をいただければというふうに思っております。\r\n　いわゆるガソリン暫定税率廃止法案について質問させていただきたいと思います。最初に、今回の暫定税率を廃止する措置をとることによってどのような効果があるのかという点について質問させていただきたいと思います。\r\n　我が国の物価は三年連続で二％を大きく上回って、上昇基調が続いています。この財金委員会で、私、日銀総裁と何回か基調的物価についての議論をさせていただきましたが、日銀の認識は基調的物価は二％をまだ上回っていないんだということでありまして、消費者物価指数は六か月連続で三％の後半、三・七％とか八％とかいう水準で推移しているので乖離があるんじゃないかというような指摘もさせていただいておりました。\r\n　中でも、エネルギー関連と食料品関連の物価がこのところ高騰していると私は認識をしておりまして、それが家計をかなり圧迫をしているんではないかというふうに思っております。\r\n　こんな調査もありました。民間の生命保険会社の調査によりますと、我が国のエンゲル係数は、二〇二四年は二八・三％で、四十三年ぶりの高水準という結果が公表をされております。所得水準の低い御家庭ほど家計に占める食費の割合が高くて、様々な要因から国民生活は大変厳しい状況に置かれているというふうに私も認識をしております。\r\n　この国民の家計は大変厳しいという切実な声に応えるために、エネルギー価格の高騰や物価を押し上げる大きな要因となっている燃料の高騰を取り除く必要があると考え、そして、特に波及効果が大きいガソリン価格を大きく引き下げることが必要ではないかということで、このガソリン暫定税率の廃止というものが国会に提出をされたものだと私は認識をしております。\r\n　物価高騰の抑制にこの暫定税率を廃止することがどのような効果を及ぼすと考えていらっしゃるのか、提案者の方にお尋ねをしたいと思います。",
      "url": "https://kokkai.ndl.go.jp/txt/121714370X02020250621/58"
    },
    {
      "date": "2025-06-21",
      "meeting": "財政金融委員会",
      "house": "参議院",
      "speaker": "熊谷裕人",
      "speech": "○熊谷裕人君　ありがとうございます。\r\n　様々なところに波及効果があるんだと、期待されている措置だというふうに私も思っております。\r\n　次の質問です。\r\n　報道によれば、総理は、一リッター当たり百七十五円をめどにまた補助金をということを表明をされているようでございますが、二〇二二年の一月から始まった燃料油価格の激変緩和措置の補助金は、二〇二四年度補正予算の一兆三百二十四億円を含めて、既に累計で八兆一千七百十九億円の補助が元売に投入をされていると私は承知をしております。\r\n　今回のガソリン暫定税率の引下げ、廃止については、この対象の燃料油から一部のものにとどまっておりますけれど、この八兆一千七百十九億円の投入額、エネ庁の資料で基にして、揮発油税、揮発油に関してどれくらいこの三年間で補助金が入れられているかというと、三兆五千百三十九億円というふうに私は承知をしております。\r\n　この措置は、一リッター当たり五円だったり二・五円だったり三・五円、そして今、二四年度の補正予算では十円という形になっておりまして、効果は限定的だというふうに思っております。\r\n　この暫定税率を廃止した場合の予算、年間必要額は一兆二百五億円というふうに承知をしておりますが、この暫定税率を廃止をした方が、二十五円十銭掛ける消費税ですから二十七円余り下がるということになりますので、はるかに投入効果というものは私は大きいというふうに思っております。\r\n　先ほど御答弁もいただきましたが、この物流コストが下がることによって様々なものが値下げになる、そういうことによって、二年連続、春闘、五％を超えて大幅な賃上げ実現しておりますが、名目賃金がずっと三年連続マイナス、そして今年に入ってからも一月から四月までマイナスというところを、この物価を抑えることでプラスに転じることができるというふうに私は考えておりまして、プラスに転じることができれば消費者マインドも変わってくるんではないのかなというふうに思っておりますので、今年の後半のＧＤＰというのも伸びていくんではないかというふうに思っております。\r\n　この予算の使い方について、今回の措置とこれまで行われておりました政府の激変緩和措置と比べてどちらが効果的と提案者は考えているか、そのお考えをお聞かせいただきたいと思います。",
      "url": "https://kokkai.ndl.go.jp/txt/121714370X02020250621/60"
    },
    {
      "date": "2025-06-21",
      "meeting": "財政金融委員会",
      "house": "参議院",
      "speaker": "熊谷裕人",
      "speech": "○熊谷裕人君　通告した質問はもう一問あったんですが、時間になりましたので、これで終わりにさせていただきたいと思います。\r\n　ありがとうございました。",
      "url": "https://kokkai.ndl.go.jp/txt/121714370X02020250621/62"
    },
    {
      "date": "2025-06-18",
      "meeting": "憲法審査会",
      "house": "参議院",
      "speaker": "熊谷裕人",
      "speech": "○熊谷裕人君　立憲民主・社民・無所属の熊谷裕人です。\r\n　国民投票法に関する意見を述べさせていただきます。\r\n　最初に、私も、さきの六月十二日の衆議院憲法審査会幹事会で四党一会派による任期延長改憲の骨子案が提出され、その後の審査会で四党一会派から臨時国会での条文化審議と条文起草委員会の設置等が意見されていることについて、少々言及させていただきます。\r\n　この骨子案について、私も拝見させていただきましたが、そもそも衆議院会派の中でオーソライズされた案なのかが明確になっていない点が一つ、そして、他の党、会派の状況に関して口を出す立場ではないことは重々承知しておりますが、提出された会派において衆議院と参議院の間でしっかりとした議論が積み重ねられ、党、会派として合意が取れた上で提出されているものかという二つの点について、私自身疑問を感じているところであります。\r\n　先ほど自民党の若林議員の方から御発言を聞かせていただきました。疑問は完全には解けませんでしたが、多少理解が進んだと思っております。\r\n　衆議院憲法審査会で自民党筆頭幹事は、これは改憲の次のステップに向けた大きな前進と言及されていますが、任期延長改憲の立法事実はあるのか、そして、任期延長改憲論がそもそもの論拠としている、参議院の緊急集会が平時の制度であり、七十日間の限定であり、二院制の例外の制度であるという説に関しては、参議院においては我が会派を始め自民党と公明党の与党もこれらの説には否定的であったと私は認識しています。\r\n　今回の衆議院憲法審査会における四党一会派の骨子案提出は、参議院憲法審査会での真摯な議論の積み重ねを根底から否定し、参議院の存在についても否定することにつながりかねない暴挙と言わざるを得ないと考えます。\r\n　以上、一言申し述べさせていただいて、国民投票法に関する会派意見に入らせていただきます。\r\n　私からは、国民投票における放送広告とインターネット規制について意見を述べたいと思います。\r\n　現行法において、表現の自由を尊重する立場から、放送広告規制は、勧誘広告は主体を問わず投票前二週間にわたり禁止されていますが、意見広告は規制されておらず、民放連による自主規制があることは承知しています。そして、インターネットに関しては規制がされておりません。\r\n　昨今のインターネット環境の激変やＡＩ技術の急速な進展と普及状況を鑑みた上で、放送広告において、ＣＭの影響力を考えれば、もはや自主規制では不十分であり、規制の見直しが必要であると考えます。さらに、インターネット利用状況の激変を考えれば、ネット広告の規制も新たな課題であると認識しています。\r\n　そこで、勧誘広告に関しては主体を問わず全運動期間にわたり禁止し、意見広告に関しては政党等に限り全運動期間にわたり禁止、また、放送事業者による公平、平等の取扱いの努力義務が必要ではないかと考えております。\r\n　また、インターネット関係では、有料のインターネット広告の規制やネットの適正利用への対処が必要であり、有料ネット広告では、政党等による有料ネット広告の禁止やネット広告事業者等による掲載基準策定の努力義務が必要だと考えております。そして、ネットの適正利用では、ネットによる勧誘、意見発信の際の表示義務や適正利用の努力義務が必要であるとも考えております。\r\n　さらに、どちらにも共通するものですが、収支報告書の提出と公表の義務や支出額の上限規制、外国勢力からの資金援助の禁止などの資金規制が必要と考えております。\r\n　次に、広報協議会の役割として、インターネット等他者が行う意見表明に関して何らかの形で関与する事務を追加するべきと考えます。\r\n　先週の参考人の方々からも意見陳述がありました。フェイク情報への対処として、広報協議会と民間団体が協力してファクトチェックを行うことや、ネット広告事業者等から影響の大きい投稿について広報協議会へ通報し、広報協議会が付随的情報を提供すること、例えば、事業者にファクトチェック対象や偽情報認定されたことを示すものを義務付けるということも必要ではないかと思っております。広報協議会として信頼性のある情報を正確に広報するなど、広報協議会の新たな機能の追加を提案するものであります。\r\n　ほかにも、過激な行動や発言でネットの視聴者を惑わし、視聴回数を稼いで収益を上げるアテンションエコノミーの問題で公正な選挙実施に大きな影響が出ていることや、ＡＩ技術の急速な進展が本物と偽物の見分けが付かないことを生じさせているディープフェイクの問題で様々な場面で大きな混乱を生じさせていること、収集された個人データに基づいて、個人の関心や趣味、嗜好に合わせて最適化された情報などがピンポイントで配信されるマイクロターゲティングの問題でフィルターバブルに陥ったり、エコーチェンバーが増幅されるリスクを生じさせることなど、国民投票法を制定した当時の状況とインターネット関連の状況は大きく様変わりしており、憲法改正を議論する前に、その手続法の一つである国民投票法の改正に真摯に取り組むべきであることを申し上げ、私の意見表明といたします。\r\n　御清聴ありがとうございました。",
      "url": "https://kokkai.ndl.go.jp/txt/121714183X00620250618/4"
    },
    {
      "date": "2025-06-03",
      "meeting": "財政金融委員会",
      "house": "参議院",
      "speaker": "熊谷裕人",
      "speech": "○熊谷裕人君　立憲民主・社民・無所属の熊谷でございます。\r\n　今、西田先生も御質問されておりましたけれど、西田先生に怒られないように、私の方からは総裁に幾つか質問させていただきたいというふうに思います。\r\n　西田先生、冒頭、四月の展望レポートの言葉を引用して質問されておりましたけれども、この展望レポートが出てもう一か月ぐらいたちました。この間に、米中の関税の高関税を掛け合うところも二転三転をしておりますし、イギリス等の間で関税について合意があったというようなことで、幾つかトランプ関税をめぐって大きな動きがあったというふうに思っております。\r\n　そしてまた、アメリカではこのトランプ関税が国際貿易裁判所で違憲だという判決を受けたということもあって、元に戻ったという見方もありますし、トランプ政権の方は一時差止めということで、またいろいろとこの裁判をめぐってでもアメリカでいろいろな動きがあります。\r\n　この相互関税ということは、その相互関税をめぐる影響が世界規模になって、かなり影響が大きいというふうに思われているのはどなたも共通したことだというふうに思っておりますけれど、その展望レポートを出して一か月たった中で、日銀としても様々なネットワークを使って情報収集をされていると思っておりますし、先月のサミットで総裁自身も各国の中央銀行総裁と意見交換をしてきたというふうに思っておりますし、引き続きの情報収集をされているのではないかなというふうに思っております。\r\n　展望レポートを出してから一か月たっている現時点での総裁としてのこの米国の関税措置をめぐる認識というものを改めてお伺いをさせていただきたいなというふうに思います。",
      "url": "https://kokkai.ndl.go.jp/txt/121714370X01520250603/27"
    },
    {
      "date": "2025-06-03",
      "meeting": "財政金融委員会",
      "house": "参議院",
      "speaker": "熊谷裕人",
      "speech": "○熊谷裕人君　今、関税率が決まったとしても不確実性は高いという御答弁をいただきました。赤澤大臣、また米国に、四回目でしたか、交渉に行って、いよいよ総理もサミットの現場でトップ会談みたいな話もありますので、日米間のその関税交渉というのも大詰めに来ているのかなと思っております。これがある程度、日米間での関税交渉というのがまとまってくれば、今不確実性という言葉ありましたけれど、日米の間でのその懸案事項というのが一つ取れていって、見通しがもう少し立つのかなというふうに思っておりますので、私も注視をしていきたいなというふうに思っております。\r\n　続いて、長期金利がここのところ急騰しているというニュースが相次いでおりまして、ちょっとそこに私も懸念を持っております。\r\n　日銀も、五月の二十一日に、機関投資家の皆さんを集めて、債券市場の関係で、生保さんだったり年金の機関投資家の皆さんから超長期金利の利回りの上昇に対する懸念を表明されたというところで、それに対応を求めるというふうに言われておりますけれど、この点について、超長期金利の急上昇に対して投資家の皆さんから何か対応してほしいということを求められていることについて、総裁の認識をお伺いしたいと思います。",
      "url": "https://kokkai.ndl.go.jp/txt/121714370X01520250603/29"
    },
    {
      "date": "2025-06-03",
      "meeting": "財政金融委員会",
      "house": "参議院",
      "speaker": "熊谷裕人",
      "speech": "○熊谷裕人君　ありがとうございます。\r\n　この超長期金利がここのところ急騰している理由の一つに買手不足というのがあるんではないのかなというふうに思っておりまして、今総裁の方から、国債の買入れの、十年物になると思うんですが、買入れの調整が今進んでいるところというのは私も理解をしておりますけれど、この超長期金利を、今まで買ってくれていた生命保険会社であったり年金の関係者がこの国債の購入を手控えているということになると、この国債の買手というのは国内でなかなか不足をしている部分もありますし、安くなったから買うという人も出てくるのかもしれませんが、海外にその買手が移るということもあるんではないかなというふうに思っておりまして、この点で、その金利との連動というものが、買手がどこになるかということで連動というところも指摘されているところだと私は認識しておりますけれど、植田総裁におかれましてはその点どのように認識をしているか、お聞かせをいただければと思います。",
      "url": "https://kokkai.ndl.go.jp/txt/121714370X01520250603/31"
    },
    {
      "date": "2025-06-03",
      "meeting": "財政金融委員会",
      "house": "参議院",
      "speaker": "熊谷裕人",
      "speech": "○熊谷裕人君　そうですね。このまま超長期国債の金利が上がっていく、いろんな資料を私も見させていただいていますけれど、かなりそのカーブがですね、イールドカーブが、何というんですか、急上昇しているという状況が、私もいろんな資料を見させていただいて、本当ここ短期間に急上昇しているのが見て取れます。\r\n　そうなってきた場合に、日本の景気というものもなかなか今混迷をしているというか、なかなか景気が上向きになっていない中で、物価高の影響もあって、様々景気の影響があって、その景気を下支えをするために、先ほど西田先生、金利を下げるという話をされていましたけれど、日銀のその追加の金利の上げるのを見送り、現状維持というようなことがここ何回か続いておりますけれど、そのようなことの蓋然性も高いのかなというふうに思うこともありますし、インフレ期待が余りにも高過ぎるので、逆に言うと利上げをして落ち着かせるんだというような判断にもつながっていくのかなというふうに私自身は思っておりまして。\r\n　ここのところについて、この超長期金利がここのところ急騰している影響というのが、日銀の金融政策に与える影響だったり日本の経済に与える影響だったりというところは本当に丁寧に分析をしていかなければいけないなというふうに思っているんですが、その辺をどのように分析をして、どのように金融政策の方向性を判断するべきなのか、改めて総裁にお伺いをさせていただきたいなというふうに思っております。\r\n　今朝、朝早く、部会に出るために着替えているときにテレビを付けていたんですけれど、ＦＲＢの幹部が、アメリカがＦＲＢとして米国の金利を年内にもう一回利下げを考えるというような発言をされたというようなニュースをちょっと着替えながら聞いておりまして、そこの、アメリカが利下げをして日本の政策金利が現状維持だったり上げていくということになると、日米の金利差が縮まって、私がかねてから言っております行き過ぎた円安の是正になっていくのかなというふうに思っているところもありますので、その辺の、その長期金利が急上昇していることが日銀の金融政策決定の方向性についてどのように影響をしていくのかというところをお尋ねをさせていただければというふうに思っております。",
      "url": "https://kokkai.ndl.go.jp/txt/121714370X01520250603/33"
    },
    {
      "date": "2025-06-03",
      "meeting": "財政金融委員会",
      "house": "参議院",
      "speaker": "熊谷裕人",
      "speech": "○熊谷裕人君　次回の金融政策決定会合で国債の買入れ減額についての中間見直しをするというふうに今御答弁をいただいておりますし、私もそこを注視をしていきたいなというふうに思っております。\r\n　国債の買手が最近本当にいないんだと、国債が売れ残るみたいなニュースも見ますので、そこは私自身も引き続き注視をしていって、その国債、いわゆる今後の政府の補正予算をどうしていくかというところにも国債の発行をどうしていくかということが私はリンクをしているんではないかなというふうに思っておりますし、先般の総理の金利のある世界を恐れると、西田先生もおっしゃっていましたけれど、そこは、ギリシャの発言があったのは、私自身は、国債発行額、累計の国債発行額がギリシャに比べて日本は倍ぐらいあってというところに注目した発言なのかなというふうに思っております。そこで国債発行に足かせが付けられてしまうことを恐れているというのが私は石破総理の本音だというふうに思っておりまして、その点についてはまた様々なところで議論をしていきたいなというふうに思っております。\r\n　続いて、為替に関する関係で、前回の質問でもさせていただきました。日銀の金融政策決定というか金融政策は円の水準にも影響を与えていくものだというふうに思っておりまして、本日の先ほどの総裁の発言の最後に二％の物価安定の目標の下でというような発言もございましたので、日銀の求めている基調的な物価上昇二％の目標というのはずっと変わらずにということであろうというふうに思っております。\r\n　為替の水準というのはなかなか、総裁だったり、日銀の皆さん、幹部の皆さんだったり、財務大臣というのはなかなか不用意に発言はできないことはよく分かっておりますし、ファンダメンタルズに沿って為替の相場は決定をされていくというのはそのとおりだというふうに思っておりますが、五月十三日に、今日出席されていませんですけれど、浅田委員が、為替相場が我が国経済に及ぼす影響については、業種あるいは企業規模、経済主体によって不均一なものであるというふうに、その浅田委員の質疑に対しての答弁がありまして、そして、為替の円高については、輸出の減少要因、あるいはグローバル企業を中心にした企業収益に悪影響を及ぼすという面もある一方で、輸入物価の低下などを通じて家計の実質所得を改善させるほか、一部の非製造業あるいは中小企業などの収益にプラスに作用する面もあるという答弁もなされているところでございます。\r\n　その点については、私もずっと行き過ぎた円安を是正することが物価高を抑えることだというふうに一貫して質問をさせていただいておりますので、その答弁というのは、そうだよね、だから為替というものをしっかりと抑制をしていかなければいけないというふうに思って、ずっと質問を続けさせていただいておりますが。\r\n　急激にこの為替が変動することは経済に悪影響もある、企業収益に悪影響もあるので、そこは避けてはいきたいなと思っておりますが、少しずつ安定的に、その為替水準をもう少し円高に是正をしていってそこで安定させるということは、企業も先行きの予測がしやすくなるので、その点を私は求めていきたいなというふうに思っておりますが。\r\n　この点、その円水準をもう少し円高に振らしていくことが、その企業だったり物価だったりというところにプラスの面があるというふうに私は本当にずっと思っておりますが、改めて総裁にその為替水準、具体的には御答弁求めませんが、ある程度今の水準よりか、それもちょっと難しいのかな、為替水準について、その物価を抑えるという認識について改めて総裁の見解を、私と同じかどうかというところをお尋ねをしたいなというふうに思っておりますが、御答弁いただけますでしょうか。よろしくお願いいたします。",
      "url": "https://kokkai.ndl.go.jp/txt/121714370X01520250603/35"
    },
    {
      "date": "2025-06-03",
      "meeting": "財政金融委員会",
      "house": "参議院",
      "speaker": "熊谷裕人",
      "speech": "○熊谷裕人君　ありがとうございます。なかなか総裁としては御答弁しにくいことだというふうに思っておりますけれど、少し前のデータになりますが、私が、多分、経団連がアンケートをされたというので、その輸出企業、そして輸入が主な企業さんを分け隔てなく、為替水準についてどれくらいがいいんだというたしかアンケートの結果が、百四十円から百四十四円ぐらいというような水準が大手の企業さんから出されていたように記憶をしておりまして、その当時は、アンケート取った当時は百六十円を超えるような円安の水準のときにアンケートを取って、そのお答えであったというふうに思っております。\r\n　輸出額が大きい自動車産業なんかはかなり収益というか、その利益への圧迫になっているというようなニュースもありますけれど、その予見ができれば、それぐらいの水準ということが予見ができれば対応できるというようなこともおっしゃっていたと思っておりますので、私自身は、今、今朝は百四十二円ぐらいだったと思いますけれど、この水準程度若しくは以下ぐらいで物価を安定させることに資するんではないかなと思っております。\r\n　ガソリンもですね、埼玉で百五十円、一リッター百五十六円なんという売値が出てまいりました。政府の元売への補助というものはあるんだと思いますが、ガソリンって一週間に一度仕切りをしていまして、割とその為替の影響というのは仕切り価格に影響が敏感に応じているところがあるので、最近のその円水準を期待というか反映をして、政府の補助も含めて一気に十円以上値下がりしているというガソリンスタンドが出てきているのかなというふうに思っておりますので、しっかりとそのやはり円水準をもう少し円高でコントロールしていくことが物価に対しては私自身はいいのかなというふうに思っておりますので、引き続き、それは私の信念として頑張っていきたいなというふうに思っております。\r\n　続いて、前回も総裁と議論させていただきました物価上昇率と、総合的な我々の認識している物価上昇率と基調的な、日銀の基調的な物価上昇率との乖離について、前回もちょっと質問させていただきましたけど、改めてもう一度、その答弁も含めて質問をさせていただきたいなというふうに思っております。\r\n　相変わらず食料品の価格の上昇が続いております。お米二千円出たというふうに、二千円の備蓄米が出ましたけれど、お米全体の値段ですると二十五円下がったなんというのがニュースになっているぐらいでありまして、生鮮食品も天候不順が回復してきたので少し値下がりをしていますが、相変わらず食料品価格というのは上昇が続いていると思います。\r\n　日銀、まあ総裁と前回も議論させていただいておりましたけれど、基調的な物価上昇率はまだ二％を下回っているんだというのが日銀の認識だというふうに私自身も思っておりますけれど、やはり、前回も言いましたけれど、私たちが感じている市場の物価の物価高、高いよねという感覚と、日銀のその基調的な物価の上昇がまだ二％を下回っているというのはかなりの乖離があるんじゃないかというふうに前回も指摘をさせていただいておりますけれど、五月二十七日に総裁が二〇二五年の国際コンファランス、カンファレンスの開会挨拶で、総合ベースで見た物価上昇率と基調的な物価上昇率の間に乖離があるというふうに認めている発言をされています。\r\n　その原因、なぜ乖離が起きてしまったのかという原因について、前回もなかなか難しい問題だというふうに御答弁をされていますけれど、改めて、この五月二十七日に総裁自身が乖離があるということを認められておりますので、その原因が何にあるのかというところをお尋ねをしたいと思います。",
      "url": "https://kokkai.ndl.go.jp/txt/121714370X01520250603/37"
    },
    {
      "date": "2025-06-03",
      "meeting": "財政金融委員会",
      "house": "参議院",
      "speaker": "熊谷裕人",
      "speech": "○熊谷裕人君　余り、何というんでしょうか、前回議論したときと変わらない感じなのかなと思っておりまして、そのときも、コミュニケーションを大切にという話もさせていただいて、コミュニケーションなかなか難しいんだよねというような御答弁をいただいたところだと思っておりますが、難しいんだよねと言うだけではなくて、様々工夫をしていかなければいけないなというふうに思っておりますが、そのコミュニケーションを取っていく、難しい中でコミュニケーションを取っていくための工夫というものを今御披露いただければ、御答弁いただければと思います。",
      "url": "https://kokkai.ndl.go.jp/txt/121714370X01520250603/39"
    },
    {
      "date": "2025-06-03",
      "meeting": "財政金融委員会",
      "house": "参議院",
      "speaker": "熊谷裕人",
      "speech": "○熊谷裕人君　ありがとうございます。\r\n　日銀の分析能力というのは私も期待をしたいと思っております。しっかり議論させていただきながら、政治の側からも、いい材料というか、議論した上でこういう判断が出るというような形のいい議論をさせていただければなというふうに思っております。\r\n　実質賃金がずっとマイナスになっている中で、政府は五年間で実質賃金一％増というのを賃上げのノルムとするというふうにこの間決定をされたようでありますけれど、その一％の、政府が目標とする一％実質賃金増ということが継続をされていくということが、日銀が金融政策を決定、判断をしていく上で、この政府の決めたノルムというものが判断材料としてどれだけ重視をされていくことになるのか。その辺は、その一％を下回った、上回ったということが金融政策への判断に影響があるかどうかというところをお尋ねしたいと思います。",
      "url": "https://kokkai.ndl.go.jp/txt/121714370X01520250603/41"
    },
    {
      "date": "2025-06-03",
      "meeting": "財政金融委員会",
      "house": "参議院",
      "speaker": "熊谷裕人",
      "speech": "○熊谷裕人君　最後の質問になろうかと思いますけれど、今、人手不足がインフレ期待に影響しているんではないかというような話がございます。\r\n　その展望レポートでも言及をされておりますけれど、人手不足感というものが予想物価の上昇、インフレ期待にどのようにつながっていくのか、その経路というものがちょっと私には分からないところもありますので、どんな業種で人手不足感が現在強まっていて、その人手不足ということがどのようにそのインフレ期待につながっていくのか、お示しをいただければと思います。",
      "url": "https://kokkai.ndl.go.jp/txt/121714370X01520250603/43"
    },
    {
      "date": "2025-06-03",
      "meeting": "財政金融委員会",
      "house": "参議院",
      "speaker": "熊谷裕人",
      "speech": "○熊谷裕人君　ありがとうございます。\r\n　本当に、人手不足のところが、アメリカではコロナが明けたときに、やっぱり人手不足で賃金が物すごく上がったことでインフレを招きました。そのようなことが起きないようにこの人手不足のところにもしっかりと我々の方からも目配りをしなければいけないなというふうに思っておりますし、この人手不足感というものを払拭するような金融政策の在り方というものがあれば一緒に考えてまいりたいというふうに思っていることを明らかにいたしまして、時間になりましたので、私の質問終わらせていただきます。\r\n　ありがとうございました。\r\n　　　　─────────────",
      "url": "https://kokkai.ndl.go.jp/txt/121714370X01520250603/45"
    },
    {
      "date": "2025-05-30",
      "meeting": "議院運営委員会",
      "house": "参議院",
      "speaker": "熊谷裕人",
      "speech": "○熊谷裕人君　ただいま動議のありました生殖補助医療法、参法を本会議で趣旨説明を聴取することなく内閣委員会に付託することの動議に反対する討論を行いたいと思います。\r\n　立憲民主・社民・無所属の熊谷裕人でございます。お願いいたします。\r\n　私は、会派を代表し、ただいまの動議に強く反対する立場から討論を行います。\r\n　まず、改めて申し上げるまでもないことですが、熟議の府参議院では、議員立法の審議について、全会一致での審議入りを原則として、与野党での丁寧な議論と合意形成に基づく運営を行ってきました。その原則を踏みにじり、多数決によって委員会付託を行うことは、当然ながら付託後の審議の在り方にも極めて重大な影響を及ぼすことを含め、反対せざるを得ません。\r\n　本法案は、我が会派に所属する議員を含む超党派の議員連盟において四年余りの歳月を掛けて検討され、今国会に四会派共同で提案されている法案であることは理解をしています。\r\n　しかしながら、出自を知る権利や、同性婚を取り巻く環境や、国民の理解、さらには司法の判断がこの一年間にも大きく進化している状況に鑑みれば、昨年段階で取りまとめられたこの議員立法がその変化を反映したものとなっているとは言えず、我が会派は、共同提出には加わらず、当事者からの法案に対する反対の声が強まっていることも踏まえ、法案自体にも反対する態度を決定させていただきました。\r\n　今、国際的にも、出自を知る権利を広く積極的に保障していくことや、法律婚ではない事実婚や同性カップルが子を授かるために生殖補助医療を利用する権利を保障することが強く求められているようになっています。\r\n　このような中で、我が国がその流れに逆行し、出自を知る権利を極めて限定的に制限し、これまで認められてきた同性婚や事実婚のカップルが子を授かる機会を奪うことは、人権や多様性を重んじる我が会派としては到底認めるわけにはいきません。\r\n　加えて、今通常国会の会期が残り実質三週間という状況で付託しようとしている内閣委員会は、いまだに閣法の審議が続いており、まだ審議入りを待っている閣法や、超党派の全会一致で提案されている議員立法も積み残されています。今ここで強引に本法案の付託を決定しても、内閣委員会で会期中に法案の審議を行える状況にはなく、そうであれば、むしろ超党派での合意形成に向けて引き続き努力を続けていくことを促すべきです。\r\n　以上の立場から、採決によって本法案を内閣委員会に付託することは強く反対することを申し上げ、反対討論といたします。",
      "url": "https://kokkai.ndl.go.jp/txt/121714024X02420250530/10"
    },
    {
      "date": "2025-05-27",
      "meeting": "財政金融委員会",
      "house": "参議院",
      "speaker": "熊谷裕人",
      "speech": "○熊谷裕人君　立憲民主・社民・無所属の熊谷裕人です。\r\n　加藤財務大臣に質問させていただきたいと思いますが、最初は、先般行われましたＧ７財務大臣・中央銀行総裁会議と、それから日米財務大臣会議について幾つか御質問させていただきたいというふうに思います。\r\n　二十日から二十二日まで行われていましたカナダでのＧ７で、アメリカのこのトランプ関税の措置というものについては明言はされていませんけれど、世界の経済にとっての不確実性が高まっているのではないかと。それから、金融政策についても世界の金融安定化に影響があるのではないかなという認識で一致をして、そして共同声明が取りまとめられたというふうに報道されております。\r\n　財務大臣が御出席をされて、各国の財務大臣と認識を共有をされているんだと思いますけれど、各国がどのような認識でこの共同声明の取りまとめに至ったのか、そして、とりわけこのアメリカの今回のトランプ関税と言われている関税政策については各国はどんなような感想を持っていたのか、これ、詳細は多分言えないと思いますが、財務大臣として、各国はどんなような感じでいたのかということをお示しできる範囲でお示しをいただければと思います。",
      "url": "https://kokkai.ndl.go.jp/txt/121714370X01320250527/7"
    },
    {
      "date": "2025-05-27",
      "meeting": "財政金融委員会",
      "house": "参議院",
      "speaker": "熊谷裕人",
      "speech": "○熊谷裕人君　アメリカのトランプ関税は保護主義的な関税だと私も思っておりますけれど、自由貿易体制を守っていくんだという認識で一致したということで理解をさせていただきたいなというふうに思います。\r\n　その後、加藤大臣は二十一日にアメリカのベッセント財務長官との会談を行っております。ベッセント長官との会談はこれで四月に続いて二回目になるというふうに思っておりますが、大臣の方から一方的なその関税措置の見直しをしてくれと強く申し入れたというふうに認識はさせていただいておりますけれど、今回の協議、このベッセント長官との協議でどのような成果が得られたのか、大臣の認識というか感想をお聞かせをいただければと思います。こんなところがしっかりと協議ができたんではないかという点について確認させていただければと思います。",
      "url": "https://kokkai.ndl.go.jp/txt/121714370X01320250527/9"
    },
    {
      "date": "2025-05-27",
      "meeting": "財政金融委員会",
      "house": "参議院",
      "speaker": "熊谷裕人",
      "speech": "○熊谷裕人君　今、大臣の方から為替については基本的なところを確認をさせていただいたというふうに御答弁をいただきましたが、本当に為替の水準については全然話をしなかったのかなというふうに思っておりまして、貿易収支の不均衡を是正をしていくんだというふうに共同声明にも書かれておりますし、日本とアメリカの間での貿易収支は日本の大幅な黒字というようなことで、そこがトランプ関税の標的に私はなっているんだというふうに思っております。ここで日米の貿易収支の改善を求めていくためには、私はやはり為替というものをある程度意識をしていかなければいけないなというふうに思っておりますけれど、急激な是正というものはアメリカも望んでいないようですし、私も、急激な是正をすると日本の経済にも影響があるというふうに思っておりますが。\r\n　最近の報道によりますと、日本は、韓国と台湾も含めてアメリカの為替の慣行に関する監視リストに入っていて、この監視リストに入っている国のうちで、日本でいえば円水準については本当にもう少し高く切り上げるべきじゃないかというようなことも要求が出てくるんではないかなというふうに思っておりまして、本当に、二回、ベッセント長官と財務大臣は協議をされておりますけれど、具体的な水準というものが、御答弁いただけないと思いますが、本当に協議をされなかったのかということに私はちょっと疑念を持っておりまして、二回とも基本的な考え方で一致をしたということではなく、もう少し突っ込んだ話があったんではないかなというふうに思っておりますが、御答弁できる範囲でその点について御答弁いただければと思います。",
      "url": "https://kokkai.ndl.go.jp/txt/121714370X01320250527/11"
    },
    {
      "date": "2025-05-27",
      "meeting": "財政金融委員会",
      "house": "参議院",
      "speaker": "熊谷裕人",
      "speech": "○熊谷裕人君　ありがとうございます。\r\n　あったとしても言えないというふうには私も思いますが、私、ずっとこの財政金融委員会で、行き過ぎた円安はやっぱり是正をしなければ物価高は止まらないというふうにずっと質疑でもさせていただいておりました。トランプ関税が世界経済に影響を与えるというようなことで今少し円高水準になってきて、先ほど確認をしましたけど、本日のレート、十時ぐらいのレートは百四十二円三十三銭、一ドルという形でありました。\r\n　私自身はもう少し円高水準でもいいかなというふうに実は個人的には思っておりまして、前々から言っているように、過度な円安は日本の物価にとって余りよろしくない、物価高を招くというふうに思っておりますが、加藤財務大臣としては、この円安というもの、円水準というものが物価にどのように影響していくのかと認識しているか、そこをお尋ねをしたいと思います。",
      "url": "https://kokkai.ndl.go.jp/txt/121714370X01320250527/13"
    },
    {
      "date": "2025-05-27",
      "meeting": "財政金融委員会",
      "house": "参議院",
      "speaker": "熊谷裕人",
      "speech": "○熊谷裕人君　なかなか予想が言い難いということでありましたけれど、私はやはりこれまでの一ドル百七十円だったり百六十円台という円水準というのは行き過ぎていると思っておりまして、その間、ちょうど、原油も一ドル九十ドルとか百ドルとかという時代がありました。今はかなり、あっ、一ドルじゃありませんね、一バレル、一バレル九十ドルとか百ドルとかということもあって日本のガソリン価格が急上昇して、それで補助金なんかも入れているわけでありますけれど、この円水準がやはりもう少し高めにというか、私自身は百四十円前後のところで安定させるのがいいというふうにかねてから言っておりますけど、その辺を目指して、しっかりと金融政策だったり為替政策だったりといったところも実施をしていっていただきたいなというふうに思っております。\r\n　次に、米国債の売却についての発言が五月二日、ゴールデンウイーク中でございましたけれど、テレビの番組で財務大臣からありました。日本は米国債の保有率は世界一であります。これを売るということで、かなりアメリカにとってもそこが売られると困ってしまうということになるので、私はある程度、そこは牽制という意味ではすごく良かったのかなというふうに思っておりますけど、財務大臣、二日後には記者会見で軌道修正をされましたが、この軌道修正をされたのは、アメリカからそこはという話があったのか、それとも大臣としてちょっと言い過ぎたという形で改めて考え方を示したのか、その辺についてお聞かせをいただければと思います。",
      "url": "https://kokkai.ndl.go.jp/txt/121714370X01320250527/15"
    },
    {
      "date": "2025-05-27",
      "meeting": "財政金融委員会",
      "house": "参議院",
      "speaker": "熊谷裕人",
      "speech": "○熊谷裕人君　私、先ほども言いましたけれど、ある程度、アメリカ国債、世界一の保有国なんだということを言うこと、必要に応じて売却もあるんだという姿勢を出すことについては、アメリカと交渉の中でも牽制という意味合いはあるんではないかなというふうに思っておりますが、その点は財務大臣はどのように、その牽制ということについての意味合いというものをもし、御答弁いただけないかもしれませんが、御発言をいただければと思います。",
      "url": "https://kokkai.ndl.go.jp/txt/121714370X01320250527/17"
    },
    {
      "date": "2025-05-27",
      "meeting": "財政金融委員会",
      "house": "参議院",
      "speaker": "熊谷裕人",
      "speech": "○熊谷裕人君　ありがとうございます。\r\n　次に、アメリカの米国債が、長期信用格付が民間の格付会社から引き下げられたという報道がありました。アメリカの国債というのは優良な格付でありましたので、安全資産とされておったと思います。\r\n　今回の格下げに、一ランク格下げになって国際金融市場にかなりの影響があるのかなというふうに思っておりましたし、実際、報道によりますとかなりの衝撃があったというふうに言われております。\r\n　今言ったように、世界一の米国債保有国である日本、この格下げの影響というものをどのように受け止めるか、お尋ねしたいと思います。",
      "url": "https://kokkai.ndl.go.jp/txt/121714370X01320250527/19"
    },
    {
      "date": "2025-05-27",
      "meeting": "財政金融委員会",
      "house": "参議院",
      "speaker": "熊谷裕人",
      "speech": "○熊谷裕人君　ありがとうございます。\r\n　引き続き戦略的に取組を進めていただきたいなというふうに思います。\r\n　次は、総理の発言についての受け止めを財務大臣にもちょっとお尋ねをしたいと思います。\r\n　石破総理、五月十九日の参議院の予算委員会で、我が国の財政状況は間違いなく極めてよろしくないと、ギリシャよりもよろしくないという状況でございますというふうに答弁をされております。\r\n　恐らく、債務残高のＧＤＰ比較を、単純にそこを見て発言をされたのかなというふうに思っておりますけれど、日本とギリシャではその経済状況や政治状況というのは全く違う状況でもありますし、財務状況も、そういった中で比較できるようなものは私は適当ではないというふうに思っておりますが、その点については財務大臣は認識どのようにお持ちなのか、お尋ねしたいと思います。",
      "url": "https://kokkai.ndl.go.jp/txt/121714370X01320250527/21"
    },
    {
      "date": "2025-05-27",
      "meeting": "財政金融委員会",
      "house": "参議院",
      "speaker": "熊谷裕人",
      "speech": "○熊谷裕人君　私も日本の財政状況というのは厳しい状況が続いているというふうに認識をさせていただいておりますけれど、私は、総理のこのギリシャよりもよろしくないという発言は、本当に不適切な発言で、失言ではないかなというふうに私自身は思っております。\r\n　この発言が基に長期金利が上がったり、これを誘発したりすると、今でも悪い日本の財政状況にかなりな悪影響があるんではないかなというふうに思っておりますが、その点については財務大臣として認識どうお持ちなのか、お尋ねしたいと思います。",
      "url": "https://kokkai.ndl.go.jp/txt/121714370X01320250527/23"
    },
    {
      "date": "2025-05-27",
      "meeting": "財政金融委員会",
      "house": "参議院",
      "speaker": "熊谷裕人",
      "speech": "○熊谷裕人君　そうですね、総理の発言というのは、ＩＭＦの債務残高のＧＤＰ比、日本は二五〇％だという数字が出ていて、ギリシャは一二五％、だから、ギリシャの倍あるから財政状況はそれだけ厳しいんだという数字に基づいて言われたんだと思いますけれど、安易にこの数字だけ言うということで、かなりな影響というものが市場にも出ているということは、より一層、その悪い方向への流れを加速をしてしまうんではないかなというふうに懸念をしておりまして、もう一度この点についてはきちんとした説明が必要なのではないかなというふうに思っておりますので、どこかでお考えをいただければ有り難いなというふうに思っております。\r\n　長期金利の急騰の影響というのもここのところございます。五月の二十一日に、日銀は、機関投資家を対象にして債券市場参加者の会合を開いております。報道によれば、その会合に参加をした大手の生命保険会社さんや年金投資家さんの方から、最近の超長金利債の利回りの上昇、急上昇過ぎるということで懸念が示されているようでございます。\r\n　その点については、超長期の金利の急騰にどのように財務省として、大臣として御対応していくつもりなのか、その認識についてお尋ねをしたいと思います。",
      "url": "https://kokkai.ndl.go.jp/txt/121714370X01320250527/25"
    },
    {
      "date": "2025-05-27",
      "meeting": "財政金融委員会",
      "house": "参議院",
      "speaker": "熊谷裕人",
      "speech": "○熊谷裕人君　その点についてはまた別の機会にもう少し深掘りをさせていただきたいなというふうに思っておりますけれど、日銀がやはり国債の買う分量というか、国債を買うことについて手控えをしている、そうしたら誰が国債を買っていくのかということになろうかと思います。\r\n　これまで買っていた生命保険会社、中期の国債だったりというところもなかなか最近は手を出さないような状況になっておりますし、この超長期のものについては、日本の将来の経済状況、財務状況というのも見通せない中で、なかなか買手がいないということになっているんではないかなというふうに思っております。\r\n　金利というところだけ見れば、預けておけばということも考えられますが、これ次回に質問させていただく予定にしておりますけれど、国債の買手というところをどう考えていくかというところにつながってくるものというふうに思っておりますので、またそれは次回に議論させていただければなというふうに思っております。\r\n　最後の質問になろうかと思います。新しい資本主義実現会議で示された実質賃金を一％増やすんだということについてお尋ねをさせていただきたいと思います。\r\n　実質賃金については三年連続マイナスの状況が続いているという状況でもありますし、ここ最近の実質賃金も、昨年の秋から暮れにかけてほんのちょっとはプラスに転じましたけれど、マイナスが続いている状況でございます。それだけ賃上げをしてもそれを上回る物価高が進行しているんだというふうに私は思っておりますので、その物価高を止めるために、私は円安を是正をしていかなければいけないというふうにずっと言わせていただいております。\r\n　この政府の目標、五年間で実質賃金一％増の賃上げノルムを実現をさせていくんだというふうに言っておりますけれど、この点について、大手さんは五％を超える賃上げが実現されたというふうに報道がありましたが、中小の賃上げはまだ四％台というようなことでもありました。ここのトランプ関税の影響もあって、今年の今の現状からいうと、中小企業の賃上げというものは息切れをしているというふうに私は思っております。\r\n　その目標を達成をしていくために一％増、プラスの実質賃金を目指すということであれば、余計物価をしっかりと抑え込んでいかなければいけないというふうに私は思っておりますが、その点について、物価高の抑制をどのように取り組んで、そして賃上げについて、目標達成のために財務大臣としてどのように取り組んでいくのか、その取組についてお尋ねをしたいと思います。",
      "url": "https://kokkai.ndl.go.jp/txt/121714370X01320250527/27"
    },
    {
      "date": "2025-05-27",
      "meeting": "財政金融委員会",
      "house": "参議院",
      "speaker": "熊谷裕人",
      "speech": "○熊谷裕人君　ありがとうございます。\r\n　本当に政策総動員をして実質賃金プラスを目指していただきたいと思いますし、そのようになるように我々も応援をしていきたいなというふうに思っておりますが、今、財務大臣の方から御答弁の中に価格転嫁というお話がありました。中小企業、特に下請さんのところは価格転嫁ができなくて、なかなかそこのコストを吸収できない、だから賃上げはできないというような状況もありますので、ここは所管ではないと思いますが、価格転嫁については、しっかり財務省、財務大臣としても、経産省だったり、公取だったりというところと連携をして、価格転嫁がスムースに進むようにしっかりとお取組をしていただきたいなというふうに思っております。\r\n　時間ちょっと残りますけれど、私の質問はこれにさせていただきたいと思います。ありがとうございました。\r\n　　　　─────────────",
      "url": "https://kokkai.ndl.go.jp/txt/121714370X01320250527/29"
    },
    {
      "date": "2025-05-15",
      "meeting": "財政金融委員会",
      "house": "参議院",
      "speaker": "熊谷裕人",
      "speech": "○熊谷裕人君　立憲民主・社民・無所属の熊谷でございます。\r\n　今、船橋委員の質問に若干重なるところありますけれど、観点違うところもありますので、改めて質問させていただきたいなというふうに思います。\r\n　財源の留保と財政資金の効率的な活用について、まずお伺いをしたいなというふうに思っております。\r\n　特別会計で、我々指摘をずっとさせていただいておりますけれど、過剰に積み上げられた剰余金や積立金があるのではないかなというふうにずっと指摘をさせていただいておりますし、政府におかれても、平成二十四年の一月二十四日に閣議決定で、特別会計改革の基本方針で、必要以上の資金を保有しないようにということで、余剰金を適切に処理することが定められております。そして、特別会計法の基本理念も同じように、過剰な留保金を積み上げないようにというような理念が規定をされているところでございます。\r\n　ところが、この法案で、投資資金勘定において決算上の剰余金を投資財源資金に組み入れて留保できるように見直すということになれば、この見直しによって、今まで守ってきた必要以上の資産を保有しないということに反して必要以上のものを持つことができるようにするというふうになりそうな懸念を持っておりまして、今まで政府が守ってきた改革の理念に反する結果になるのではないかなというふうに思っておりますが、その点について財務大臣はどのようにお考えか、認識を伺いたいと思います。",
      "url": "https://kokkai.ndl.go.jp/txt/121714370X01220250515/16"
    },
    {
      "date": "2025-05-15",
      "meeting": "財政金融委員会",
      "house": "参議院",
      "speaker": "熊谷裕人",
      "speech": "○熊谷裕人君　今回のこの改正は、財投資金の留保をして、産業投資をより安定的、機動的に運営していくために柔軟性を確保したいというのが目的となっているというのは理解をしておりますが、歳入を大幅に超える資金需要が発生したのであれば、その都度一般会計から投資勘定に必要な金額を繰り入れて賄うということもできるのではないかなというふうに思っておりますし、従来もそのようなことがされていたんではないかなというふうに思っております。\r\n　産業投資資金については、その年度における配当金だったり納付金などの範囲で行うというのをやはり基本にして、必要であれば一般会計から繰り入れるというのが私は望ましいというふうに思っておるんですが、その点についての財務大臣の見解をお伺いをしたいのと、それから、本法案によって財投資金への財源の留保が可能ということになれば、通常の歳入を超える資金需要が発生した場合にも投資勘定において自立的、安定的、機動的に財源を確保できるというふうに言われております。しかし、これは裏を返せば、一般会計がどんなに厳しい状況であっても投資勘定においてはその留保金があるので、厳しい査定や検討という国会の関与をその場で受けることなく産業投資の財源を確保できるということになるんではないかなというふうに思っております。\r\n　先ほど船橋さんの質問にもありました、かつて自民党の塩川元財務大臣が母屋でおかゆ、離れですき焼きという言葉を残しておられますけれど、財務省の若手の官僚はその言葉を聞いたこともないというような方も今ではいるというのを、ちょっと話をしてみて、あっ、若い人たちはこの言葉知らないんだというのを改めて私も認識したところであります。だからこそ、先ほど、これまでの特別会計改革の流れに逆行するんではないかなというような質問をさせていただいたところでございます。\r\n　やはり、投資勘定に投資需要を一般会計からの繰入れで賄うということになるのであれば、いつ使うか分からない財源を投資財源資金に寝かしておくようなことにやはり私はなるんではないかなというふうに思っておりまして、効率的に活用ができて、一般会計の財政状況やほかの政策の財源確保の状況を踏まえながら検討をしっかりとやはり国会でも行っていくべきだというふうに思っておりますが、一般会計との関係を財務大臣はどのように思っているのか、認識をお伺いしたいと思います。",
      "url": "https://kokkai.ndl.go.jp/txt/121714370X01220250515/18"
    },
    {
      "date": "2025-05-15",
      "meeting": "財政金融委員会",
      "house": "参議院",
      "speaker": "熊谷裕人",
      "speech": "○熊谷裕人君　ありがとうございます。\r\n　今日は質問で余りやらないようにしようと思っているんですけど、官民ファンド、やはり我々、官民ファンドはなかなか国会のチェックやガバナンスが利かない部分であるというふうに度々指摘をさせていただいておりますけれど、留保金を国会に諮らないで使えるようにするということは、その官民ファンドのように自由に国会のガバナンスが届かないところで使われてしまうという二の舞にならないように、しっかりと我々も監視をしていかなければいけないなというふうに思っております。\r\n　次に、産業投資の安定的な運営についてお伺いをさせていただきたいと思います。\r\n　今、余裕のあるときには財源を留保し、そして歳入に余裕がないときにはその投資財源の財源を活用したり借入れを行ったりするということで、安定的な、機動的な産業投資を可能にしようという目的で今度はこの法改正が行われることでありますけれど、今度の法改正の内容がもし実施をされる、施行されることになれば、毎年度の資金需要は満たしやすくなりますし、安定的な資金供給が達成できるのかもしれませんけれど、その反面、歳入による制約は掛かりにくくなるんではないかなというふうに懸念をしておりまして、年度ごとの産業投資の規模、そして歳出側である資金需要によって、それはかなり恣意的というのか、そのときの状況によって変動することになるんではないかなというふうにちょっと考えておりまして、その結果、一時的に資金需要が高まった特定の産業にこのリスクマネーの投資というものが集中的というか、特定のところに集中して投資が行われるというようなことも行われてしまうリスクがあるんではないかなというふうに思っておりまして、財投の持つ投資先のリスク分散というところが利かなくなってしまうのではないかなという懸念を持っているんですが、その点については財務大臣どのようにお考えか、お伺いしたいと思います。",
      "url": "https://kokkai.ndl.go.jp/txt/121714370X01220250515/20"
    },
    {
      "date": "2025-05-15",
      "meeting": "財政金融委員会",
      "house": "参議院",
      "speaker": "熊谷裕人",
      "speech": "○熊谷裕人君　ありがとうございます。\r\n　平準化するという御答弁をいただきましたが、元々、産業投資というのは、中長期的な視野でやはりリスクとリターンというものを考えながら、民間投資の呼び水にしていくような点を踏まえなければいけないものだというふうに思っておりますので、そこは計画的に投資というものが行われるのが求められておりまして、この法改正による機動的に実施しなければいけない出資というのはなかなか私には想定しにくいところなんですが、産業投資において機動的に出資をしなければいけないというものを政府としてはどのように具体的に想定をしているのか、そして、今まで機動的に出資ができずに、応援しようと思っていた産業の成長や発展に支障を来したというような具体的な事例があるのかどうか、お聞かせをいただければと思います。",
      "url": "https://kokkai.ndl.go.jp/txt/121714370X01220250515/22"
    },
    {
      "date": "2025-05-15",
      "meeting": "財政金融委員会",
      "house": "参議院",
      "speaker": "熊谷裕人",
      "speech": "○熊谷裕人君　何となく分かるような分かんないような気が私はしてならないんですけれど。\r\n　年度途中に発生した資金需要は、補正予算で一般会計から投資勘定に繰入れを行ったという例もあるというふうに聞いておりますけれど、現状でも、借入れや留保金という制度をつくらなくても機動的な資金調達をできるんではないかなというふうに考えておりますし、今の御答弁だと、今まで対応できなかったという事例はないという御答弁でもありましたので、もう一度、なぜ現状では不十分であるのかという点について、機動的な資金調達が本当に必要なんだというところについて、もう一度御答弁いただければと思います。",
      "url": "https://kokkai.ndl.go.jp/txt/121714370X01220250515/24"
    },
    {
      "date": "2025-05-15",
      "meeting": "財政金融委員会",
      "house": "参議院",
      "speaker": "熊谷裕人",
      "speech": "○熊谷裕人君　ありがとうございます。\r\n　特別会計の中だけでその資金繰りというか、しっかりと回していくというのはよく分かるんですけれど、特別会計に余裕があって、一般会計が厳しいから、逆に特別会計から一般会計に資金をというようなことも、我々、よくいろんなところの財源で特別会計のこの余剰資金を使うべきだというような話を立憲民主党としてはさせていただいておりますし、今はそういうことが可能であるというふうに認識をしておりますけれど、これが変わって、この法改正になると、逆に言うと、一般会計が苦しいから特会から一般会計に入れるということがなかなか、留保金で持ってますよということで、しにくくなるのかなというふうに思いますし、政府としてもそういう言い方になってしまうんではないのかなというふうに、その点を強く懸念しているところでございます。\r\n　次に、借入先についてなんですが、民間金融機関から借入れを行う方法と、それから財投債なんかで資金調達をしているということが方法としてあるんではないかなというふうに思っております。この法案の改正で新たに可能になる投資勘定の借入れについては財政融資資金からの借入れを想定しているものと理解をしていいのかどうか、そして借入れの期間についてはどの程度を想定をしているのか、お聞かせをいただければと思います。",
      "url": "https://kokkai.ndl.go.jp/txt/121714370X01220250515/26"
    },
    {
      "date": "2025-05-15",
      "meeting": "財政金融委員会",
      "house": "参議院",
      "speaker": "熊谷裕人",
      "speech": "○熊谷裕人君　そうすると、今最大十年という話がありましたけれど、その期間について、政府というか国会が関与をするチャンスというのはあるんでしょうか。ちょっとこの点、もしお答えいただけるようでしたらお答えをいただければと思います。",
      "url": "https://kokkai.ndl.go.jp/txt/121714370X01220250515/28"
    },
    {
      "date": "2025-05-15",
      "meeting": "財政金融委員会",
      "house": "参議院",
      "speaker": "熊谷裕人",
      "speech": "○熊谷裕人君　ありがとうございます。\r\n　国会が知らないところで五年だ、十年だと決められても困るなというふうに思ったので、ちょっと御答弁いただいたことに質問させていただきました。\r\n　ちょっと時間がなくなってきてしまったので、もう一つ、リスクの高い、リスクマネーの供給ということになっているので、財政融資資金というところから借り入れるということになると、本来であれば手堅い投資というものが行われていた財政融資資金もリスクにさらされることになるんではないかなというふうに思っておりまして、そういう安定性が損なわれるおそれがある、ですけれど、融資先としてその財政融資資金を選んだ理由というものについて説明をいただければと思います。",
      "url": "https://kokkai.ndl.go.jp/txt/121714370X01220250515/30"
    },
    {
      "date": "2025-05-15",
      "meeting": "財政金融委員会",
      "house": "参議院",
      "speaker": "熊谷裕人",
      "speech": "○熊谷裕人君　最後の質問になりますが、借入額と留保額についてのところの懸念についてもう一度お尋ねをしたいと思いますけれど、審議会にその留保額、借入額については試算と目安額を示してしっかりと説明をしていくというふうに国会でも御答弁をされております。具体的にどのような検討が行われるのか、そしてその検討の内容については、上限額の妥当性なんかについてどのように担保するつもりなのか、財務大臣の見解をお伺いしたいと思います。",
      "url": "https://kokkai.ndl.go.jp/txt/121714370X01220250515/32"
    }
  ]
}